DEFINE PUBLIC <init>()V
ALIAS H_META "handle[H_INVOKESTATIC java/lang/invoke/LambdaMetafactory.metafactory(Ljava/lang/invoke/MethodHandles$Lookup;Ljava/lang/String;Ljava/lang/invoke/MethodType;Ljava/lang/invoke/MethodType;Ljava/lang/invoke/MethodHandle;Ljava/lang/invoke/MethodType;)Ljava/lang/invoke/CallSite;]"
A:
ALOAD this
INVOKESPECIAL javax/swing/JFrame.<init>()V
ALOAD this
NEW cl
DUP
INVOKESPECIAL cl.<init>()V
PUTFIELD ax.a Lcl;
ALOAD this
NEW cv
DUP
INVOKESPECIAL cv.<init>()V
PUTFIELD ax.a Lcv;
ALOAD this
NEW cs
DUP
INVOKESPECIAL cs.<init>()V
PUTFIELD ax.a Lcs;
ALOAD this
NEW bl
DUP
INVOKESPECIAL bl.<init>()V
PUTFIELD ax.a Lbl;
ALOAD this
NEW aU
DUP
INVOKESPECIAL aU.<init>()V
PUTFIELD ax.a LaU;
ALOAD this
NEW cf
DUP
INVOKESPECIAL cf.<init>()V
PUTFIELD ax.a Lcf;
ALOAD this
NEW cm
DUP
INVOKESPECIAL cm.<init>()V
PUTFIELD ax.a Lcm;
ALOAD this
NEW bI
DUP
INVOKESPECIAL bI.<init>()V
PUTFIELD ax.a LbI;
ALOAD this
NEW cM
DUP
INVOKESPECIAL cM.<init>()V
PUTFIELD ax.a LcM;
ALOAD this
NEW aR
DUP
ALOAD this
ICONST_0
INVOKESPECIAL aR.<init>(Lax;B)V
PUTFIELD ax.a LaR;
ALOAD this
NEW java/util/ArrayList
DUP
INVOKESPECIAL java/util/ArrayList.<init>()V
PUTFIELD ax.a Ljava/util/List;
ALOAD this
DUP
ASTORE 1
NEW javax/swing/JPanel
DUP
INVOKESPECIAL javax/swing/JPanel.<init>()V
PUTFIELD ax.c Ljavax/swing/JPanel;
ALOAD 1
NEW javax/swing/JPanel
DUP
INVOKESPECIAL javax/swing/JPanel.<init>()V
PUTFIELD ax.e Ljavax/swing/JPanel;
ALOAD 1
NEW javax/swing/JButton
DUP
INVOKESPECIAL javax/swing/JButton.<init>()V
PUTFIELD ax.c Ljavax/swing/JButton;
ALOAD 1
NEW javax/swing/JButton
DUP
INVOKESPECIAL javax/swing/JButton.<init>()V
PUTFIELD ax.a Ljavax/swing/JButton;
ALOAD 1
NEW javax/swing/JButton
DUP
INVOKESPECIAL javax/swing/JButton.<init>()V
PUTFIELD ax.b Ljavax/swing/JButton;
ALOAD 1
NEW javax/swing/JLabel
DUP
INVOKESPECIAL javax/swing/JLabel.<init>()V
PUTFIELD ax.b Ljavax/swing/JLabel;
ALOAD 1
NEW javax/swing/JPanel
DUP
INVOKESPECIAL javax/swing/JPanel.<init>()V
PUTFIELD ax.b Ljavax/swing/JPanel;
ALOAD 1
NEW javax/swing/JPanel
DUP
INVOKESPECIAL javax/swing/JPanel.<init>()V
PUTFIELD ax.a Ljavax/swing/JPanel;
ALOAD 1
NEW javax/swing/JComboBox
DUP
INVOKESPECIAL javax/swing/JComboBox.<init>()V
PUTFIELD ax.a Ljavax/swing/JComboBox;
ALOAD 1
NEW cT
DUP
INVOKESPECIAL cT.<init>()V
PUTFIELD ax.a LcT;
ALOAD 1
NEW cP
DUP
INVOKESPECIAL cP.<init>()V
PUTFIELD ax.d LcP;
ALOAD 1
NEW cP
DUP
INVOKESPECIAL cP.<init>()V
PUTFIELD ax.b LcP;
ALOAD 1
NEW cP
DUP
INVOKESPECIAL cP.<init>()V
PUTFIELD ax.a LcP;
ALOAD 1
NEW cP
DUP
INVOKESPECIAL cP.<init>()V
PUTFIELD ax.c LcP;
ALOAD 1
NEW cP
DUP
INVOKESPECIAL cP.<init>()V
PUTFIELD ax.h LcP;
ALOAD 1
NEW cP
DUP
INVOKESPECIAL cP.<init>()V
PUTFIELD ax.f LcP;
ALOAD 1
NEW cP
DUP
INVOKESPECIAL cP.<init>()V
PUTFIELD ax.e LcP;
ALOAD 1
NEW cP
DUP
INVOKESPECIAL cP.<init>()V
PUTFIELD ax.i LcP;
ALOAD 1
NEW cP
DUP
INVOKESPECIAL cP.<init>()V
PUTFIELD ax.g LcP;
ALOAD 1
NEW javax/swing/JPanel
DUP
INVOKESPECIAL javax/swing/JPanel.<init>()V
PUTFIELD ax.f Ljavax/swing/JPanel;
ALOAD 1
NEW javax/swing/JTextField
DUP
INVOKESPECIAL javax/swing/JTextField.<init>()V
PUTFIELD ax.a Ljavax/swing/JTextField;
ALOAD 1
NEW javax/swing/JFormattedTextField
DUP
INVOKESPECIAL javax/swing/JFormattedTextField.<init>()V
PUTFIELD ax.a Ljavax/swing/JFormattedTextField;
ALOAD 1
NEW dc
DUP
INVOKESPECIAL dc.<init>()V
PUTFIELD ax.a Ldc;
ALOAD 1
NEW dc
DUP
INVOKESPECIAL dc.<init>()V
PUTFIELD ax.b Ldc;
ALOAD 1
NEW javax/swing/JPanel
DUP
INVOKESPECIAL javax/swing/JPanel.<init>()V
PUTFIELD ax.d Ljavax/swing/JPanel;
ALOAD 1
NEW javax/swing/JLabel
DUP
INVOKESPECIAL javax/swing/JLabel.<init>()V
PUTFIELD ax.a Ljavax/swing/JLabel;
ALOAD 1
NEW javax/swing/JSeparator
DUP
INVOKESPECIAL javax/swing/JSeparator.<init>()V
PUTFIELD ax.a Ljavax/swing/JSeparator;
ALOAD 1
NEW javax/swing/JProgressBar
DUP
INVOKESPECIAL javax/swing/JProgressBar.<init>()V
PUTFIELD ax.a Ljavax/swing/JProgressBar;
ALOAD 1
NEW javax/swing/JLabel
DUP
INVOKESPECIAL javax/swing/JLabel.<init>()V
PUTFIELD ax.c Ljavax/swing/JLabel;
ALOAD 1
ICONST_0
INVOKEVIRTUAL ax.setDefaultCloseOperation(I)V
ALOAD 1
LDC "MobyDroid"
INVOKEVIRTUAL ax.setTitle(Ljava/lang/String;)V
ALOAD 1
NEW java/awt/Dimension
DUP
SIPUSH 1024
SIPUSH 496
INVOKESPECIAL java/awt/Dimension.<init>(II)V
INVOKEVIRTUAL ax.setMinimumSize(Ljava/awt/Dimension;)V
ALOAD 1
LDC "MainFrame"
INVOKEVIRTUAL ax.setName(Ljava/lang/String;)V
ALOAD 1
ICONST_1
INVOKEVIRTUAL ax.setUndecorated(Z)V
ALOAD 1
NEW java/awt/Dimension
DUP
ICONST_0
ICONST_0
INVOKESPECIAL java/awt/Dimension.<init>(II)V
INVOKEVIRTUAL ax.setSize(Ljava/awt/Dimension;)V
ALOAD 1
NEW aJ
DUP
ALOAD 1
INVOKESPECIAL aJ.<init>(Lax;)V
INVOKEVIRTUAL ax.addWindowListener(Ljava/awt/event/WindowListener;)V
ALOAD 1
GETFIELD ax.c Ljavax/swing/JPanel;
NEW java/awt/Color
DUP
SIPUSH 250
SIPUSH 250
SIPUSH 250
INVOKESPECIAL java/awt/Color.<init>(III)V
INVOKEVIRTUAL javax/swing/JPanel.setBackground(Ljava/awt/Color;)V
ALOAD 1
GETFIELD ax.e Ljavax/swing/JPanel;
NEW java/awt/Color
DUP
BIPUSH 25
BIPUSH 118
SIPUSH 210
INVOKESPECIAL java/awt/Color.<init>(III)V
INVOKEVIRTUAL javax/swing/JPanel.setBackground(Ljava/awt/Color;)V
ALOAD 1
GETFIELD ax.e Ljavax/swing/JPanel;
NEW java/awt/Color
DUP
BIPUSH 25
BIPUSH 118
SIPUSH 210
INVOKESPECIAL java/awt/Color.<init>(III)V
INVOKESTATIC javax/swing/BorderFactory.createLineBorder(Ljava/awt/Color;)Ljavax/swing/border/Border;
INVOKEVIRTUAL javax/swing/JPanel.setBorder(Ljavax/swing/border/Border;)V
ALOAD 1
GETFIELD ax.c Ljavax/swing/JButton;
NEW java/awt/Color
DUP
BIPUSH 25
BIPUSH 118
SIPUSH 210
INVOKESPECIAL java/awt/Color.<init>(III)V
INVOKEVIRTUAL javax/swing/JButton.setBackground(Ljava/awt/Color;)V
ALOAD 1
GETFIELD ax.c Ljavax/swing/JButton;
GETSTATIC Y.a Ljava/awt/Font;
LDC 20.0F
INVOKEVIRTUAL java/awt/Font.deriveFont(F)Ljava/awt/Font;
INVOKEVIRTUAL javax/swing/JButton.setFont(Ljava/awt/Font;)V
ALOAD 1
GETFIELD ax.c Ljavax/swing/JButton;
NEW java/awt/Color
DUP
SIPUSH 255
SIPUSH 255
SIPUSH 255
INVOKESPECIAL java/awt/Color.<init>(III)V
INVOKEVIRTUAL javax/swing/JButton.setForeground(Ljava/awt/Color;)V
ALOAD 1
GETFIELD ax.c Ljavax/swing/JButton;
LDC ""
INVOKEVIRTUAL javax/swing/JButton.setText(Ljava/lang/String;)V
ALOAD 1
GETFIELD ax.c Ljavax/swing/JButton;
LDC "Minimize"
INVOKEVIRTUAL javax/swing/JButton.setToolTipText(Ljava/lang/String;)V
ALOAD 1
GETFIELD ax.c Ljavax/swing/JButton;
NEW java/awt/Color
DUP
ICONST_0
ICONST_0
ICONST_0
INVOKESPECIAL java/awt/Color.<init>(III)V
INVOKESTATIC javax/swing/BorderFactory.createLineBorder(Ljava/awt/Color;)Ljavax/swing/border/Border;
INVOKEVIRTUAL javax/swing/JButton.setBorder(Ljavax/swing/border/Border;)V
ALOAD 1
GETFIELD ax.c Ljavax/swing/JButton;
ICONST_0
INVOKEVIRTUAL javax/swing/JButton.setBorderPainted(Z)V
ALOAD 1
GETFIELD ax.c Ljavax/swing/JButton;
NEW aK
DUP
ALOAD 1
INVOKESPECIAL aK.<init>(Lax;)V
INVOKEVIRTUAL javax/swing/JButton.addActionListener(Ljava/awt/event/ActionListener;)V
ALOAD 1
GETFIELD ax.a Ljavax/swing/JButton;
NEW java/awt/Color
DUP
BIPUSH 25
BIPUSH 118
SIPUSH 210
INVOKESPECIAL java/awt/Color.<init>(III)V
INVOKEVIRTUAL javax/swing/JButton.setBackground(Ljava/awt/Color;)V
ALOAD 1
GETFIELD ax.a Ljavax/swing/JButton;
GETSTATIC Y.a Ljava/awt/Font;
LDC 20.0F
INVOKEVIRTUAL java/awt/Font.deriveFont(F)Ljava/awt/Font;
INVOKEVIRTUAL javax/swing/JButton.setFont(Ljava/awt/Font;)V
ALOAD 1
GETFIELD ax.a Ljavax/swing/JButton;
NEW java/awt/Color
DUP
SIPUSH 255
SIPUSH 255
SIPUSH 255
INVOKESPECIAL java/awt/Color.<init>(III)V
INVOKEVIRTUAL javax/swing/JButton.setForeground(Ljava/awt/Color;)V
ALOAD 1
GETFIELD ax.a Ljavax/swing/JButton;
LDC ""
INVOKEVIRTUAL javax/swing/JButton.setText(Ljava/lang/String;)V
ALOAD 1
GETFIELD ax.a Ljavax/swing/JButton;
LDC "Exit"
INVOKEVIRTUAL javax/swing/JButton.setToolTipText(Ljava/lang/String;)V
ALOAD 1
GETFIELD ax.a Ljavax/swing/JButton;
NEW java/awt/Color
DUP
ICONST_0
ICONST_0
ICONST_0
INVOKESPECIAL java/awt/Color.<init>(III)V
INVOKESTATIC javax/swing/BorderFactory.createLineBorder(Ljava/awt/Color;)Ljavax/swing/border/Border;
INVOKEVIRTUAL javax/swing/JButton.setBorder(Ljavax/swing/border/Border;)V
ALOAD 1
GETFIELD ax.a Ljavax/swing/JButton;
ICONST_0
INVOKEVIRTUAL javax/swing/JButton.setBorderPainted(Z)V
ALOAD 1
GETFIELD ax.a Ljavax/swing/JButton;
NEW aL
DUP
ALOAD 1
INVOKESPECIAL aL.<init>(Lax;)V
INVOKEVIRTUAL javax/swing/JButton.addActionListener(Ljava/awt/event/ActionListener;)V
ALOAD 1
GETFIELD ax.b Ljavax/swing/JButton;
NEW java/awt/Color
DUP
BIPUSH 25
BIPUSH 118
SIPUSH 210
INVOKESPECIAL java/awt/Color.<init>(III)V
INVOKEVIRTUAL javax/swing/JButton.setBackground(Ljava/awt/Color;)V
ALOAD 1
GETFIELD ax.b Ljavax/swing/JButton;
GETSTATIC Y.a Ljava/awt/Font;
LDC 20.0F
INVOKEVIRTUAL java/awt/Font.deriveFont(F)Ljava/awt/Font;
INVOKEVIRTUAL javax/swing/JButton.setFont(Ljava/awt/Font;)V
ALOAD 1
GETFIELD ax.b Ljavax/swing/JButton;
NEW java/awt/Color
DUP
SIPUSH 255
SIPUSH 255
SIPUSH 255
INVOKESPECIAL java/awt/Color.<init>(III)V
INVOKEVIRTUAL javax/swing/JButton.setForeground(Ljava/awt/Color;)V
ALOAD 1
GETFIELD ax.b Ljavax/swing/JButton;
LDC ""
INVOKEVIRTUAL javax/swing/JButton.setText(Ljava/lang/String;)V
ALOAD 1
GETFIELD ax.b Ljavax/swing/JButton;
LDC "Maximize"
INVOKEVIRTUAL javax/swing/JButton.setToolTipText(Ljava/lang/String;)V
ALOAD 1
GETFIELD ax.b Ljavax/swing/JButton;
NEW java/awt/Color
DUP
ICONST_0
ICONST_0
ICONST_0
INVOKESPECIAL java/awt/Color.<init>(III)V
INVOKESTATIC javax/swing/BorderFactory.createLineBorder(Ljava/awt/Color;)Ljavax/swing/border/Border;
INVOKEVIRTUAL javax/swing/JButton.setBorder(Ljavax/swing/border/Border;)V
ALOAD 1
GETFIELD ax.b Ljavax/swing/JButton;
ICONST_0
INVOKEVIRTUAL javax/swing/JButton.setBorderPainted(Z)V
ALOAD 1
GETFIELD ax.b Ljavax/swing/JButton;
NEW aM
DUP
ALOAD 1
INVOKESPECIAL aM.<init>(Lax;)V
INVOKEVIRTUAL javax/swing/JButton.addActionListener(Ljava/awt/event/ActionListener;)V
ALOAD 1
GETFIELD ax.b Ljavax/swing/JLabel;
NEW java/awt/Font
DUP
LDC "Dialog"
ICONST_1
BIPUSH 18
INVOKESPECIAL java/awt/Font.<init>(Ljava/lang/String;II)V
INVOKEVIRTUAL javax/swing/JLabel.setFont(Ljava/awt/Font;)V
ALOAD 1
GETFIELD ax.b Ljavax/swing/JLabel;
NEW java/awt/Color
DUP
SIPUSH 255
SIPUSH 255
SIPUSH 255
INVOKESPECIAL java/awt/Color.<init>(III)V
INVOKEVIRTUAL javax/swing/JLabel.setForeground(Ljava/awt/Color;)V
ALOAD 1
GETFIELD ax.b Ljavax/swing/JLabel;
LDC "MobyDroid"
INVOKEVIRTUAL javax/swing/JLabel.setText(Ljava/lang/String;)V
NEW javax/swing/GroupLayout
DUP
ALOAD 1
GETFIELD ax.e Ljavax/swing/JPanel;
INVOKESPECIAL javax/swing/GroupLayout.<init>(Ljava/awt/Container;)V
ASTORE 2
ALOAD 1
GETFIELD ax.e Ljavax/swing/JPanel;
ALOAD 2
INVOKEVIRTUAL javax/swing/JPanel.setLayout(Ljava/awt/LayoutManager;)V
ALOAD 2
DUP
GETSTATIC javax/swing/GroupLayout$Alignment.LEADING Ljavax/swing/GroupLayout$Alignment;
INVOKEVIRTUAL javax/swing/GroupLayout.createParallelGroup(Ljavax/swing/GroupLayout$Alignment;)Ljavax/swing/GroupLayout$ParallelGroup;
GETSTATIC javax/swing/GroupLayout$Alignment.TRAILING Ljavax/swing/GroupLayout$Alignment;
ALOAD 2
INVOKEVIRTUAL javax/swing/GroupLayout.createSequentialGroup()Ljavax/swing/GroupLayout$SequentialGroup;
INVOKEVIRTUAL javax/swing/GroupLayout$SequentialGroup.addContainerGap()Ljavax/swing/GroupLayout$SequentialGroup;
ALOAD 1
GETFIELD ax.b Ljavax/swing/JLabel;
ICONST_M1
ICONST_M1
SIPUSH 32767
INVOKEVIRTUAL javax/swing/GroupLayout$SequentialGroup.addComponent(Ljava/awt/Component;III)Ljavax/swing/GroupLayout$SequentialGroup;
GETSTATIC javax/swing/LayoutStyle$ComponentPlacement.RELATED Ljavax/swing/LayoutStyle$ComponentPlacement;
INVOKEVIRTUAL javax/swing/GroupLayout$SequentialGroup.addPreferredGap(Ljavax/swing/LayoutStyle$ComponentPlacement;)Ljavax/swing/GroupLayout$SequentialGroup;
ALOAD 1
GETFIELD ax.c Ljavax/swing/JButton;
BIPUSH -2
BIPUSH 32
BIPUSH -2
INVOKEVIRTUAL javax/swing/GroupLayout$SequentialGroup.addComponent(Ljava/awt/Component;III)Ljavax/swing/GroupLayout$SequentialGroup;
GETSTATIC javax/swing/LayoutStyle$ComponentPlacement.RELATED Ljavax/swing/LayoutStyle$ComponentPlacement;
INVOKEVIRTUAL javax/swing/GroupLayout$SequentialGroup.addPreferredGap(Ljavax/swing/LayoutStyle$ComponentPlacement;)Ljavax/swing/GroupLayout$SequentialGroup;
ALOAD 1
GETFIELD ax.b Ljavax/swing/JButton;
BIPUSH -2
BIPUSH 32
BIPUSH -2
INVOKEVIRTUAL javax/swing/GroupLayout$SequentialGroup.addComponent(Ljava/awt/Component;III)Ljavax/swing/GroupLayout$SequentialGroup;
GETSTATIC javax/swing/LayoutStyle$ComponentPlacement.RELATED Ljavax/swing/LayoutStyle$ComponentPlacement;
INVOKEVIRTUAL javax/swing/GroupLayout$SequentialGroup.addPreferredGap(Ljavax/swing/LayoutStyle$ComponentPlacement;)Ljavax/swing/GroupLayout$SequentialGroup;
ALOAD 1
GETFIELD ax.a Ljavax/swing/JButton;
BIPUSH -2
BIPUSH 32
BIPUSH -2
INVOKEVIRTUAL javax/swing/GroupLayout$SequentialGroup.addComponent(Ljava/awt/Component;III)Ljavax/swing/GroupLayout$SequentialGroup;
INVOKEVIRTUAL javax/swing/GroupLayout$SequentialGroup.addContainerGap()Ljavax/swing/GroupLayout$SequentialGroup;
INVOKEVIRTUAL javax/swing/GroupLayout$ParallelGroup.addGroup(Ljavax/swing/GroupLayout$Alignment;Ljavax/swing/GroupLayout$Group;)Ljavax/swing/GroupLayout$ParallelGroup;
INVOKEVIRTUAL javax/swing/GroupLayout.setHorizontalGroup(Ljavax/swing/GroupLayout$Group;)V
ALOAD 2
DUP
GETSTATIC javax/swing/GroupLayout$Alignment.LEADING Ljavax/swing/GroupLayout$Alignment;
INVOKEVIRTUAL javax/swing/GroupLayout.createParallelGroup(Ljavax/swing/GroupLayout$Alignment;)Ljavax/swing/GroupLayout$ParallelGroup;
ALOAD 2
INVOKEVIRTUAL javax/swing/GroupLayout.createSequentialGroup()Ljavax/swing/GroupLayout$SequentialGroup;
BIPUSH 6
BIPUSH 6
BIPUSH 6
INVOKEVIRTUAL javax/swing/GroupLayout$SequentialGroup.addGap(III)Ljavax/swing/GroupLayout$SequentialGroup;
ALOAD 2
GETSTATIC javax/swing/GroupLayout$Alignment.TRAILING Ljavax/swing/GroupLayout$Alignment;
INVOKEVIRTUAL javax/swing/GroupLayout.createParallelGroup(Ljavax/swing/GroupLayout$Alignment;)Ljavax/swing/GroupLayout$ParallelGroup;
ALOAD 1
GETFIELD ax.b Ljavax/swing/JLabel;
BIPUSH -2
BIPUSH 32
BIPUSH -2
INVOKEVIRTUAL javax/swing/GroupLayout$ParallelGroup.addComponent(Ljava/awt/Component;III)Ljavax/swing/GroupLayout$ParallelGroup;
GETSTATIC javax/swing/GroupLayout$Alignment.LEADING Ljavax/swing/GroupLayout$Alignment;
ALOAD 2
GETSTATIC javax/swing/GroupLayout$Alignment.BASELINE Ljavax/swing/GroupLayout$Alignment;
INVOKEVIRTUAL javax/swing/GroupLayout.createParallelGroup(Ljavax/swing/GroupLayout$Alignment;)Ljavax/swing/GroupLayout$ParallelGroup;
ALOAD 1
GETFIELD ax.b Ljavax/swing/JButton;
BIPUSH -2
BIPUSH 32
BIPUSH -2
INVOKEVIRTUAL javax/swing/GroupLayout$ParallelGroup.addComponent(Ljava/awt/Component;III)Ljavax/swing/GroupLayout$ParallelGroup;
ALOAD 1
GETFIELD ax.a Ljavax/swing/JButton;
BIPUSH -2
BIPUSH 32
BIPUSH -2
INVOKEVIRTUAL javax/swing/GroupLayout$ParallelGroup.addComponent(Ljava/awt/Component;III)Ljavax/swing/GroupLayout$ParallelGroup;
ALOAD 1
GETFIELD ax.c Ljavax/swing/JButton;
BIPUSH -2
BIPUSH 32
BIPUSH -2
INVOKEVIRTUAL javax/swing/GroupLayout$ParallelGroup.addComponent(Ljava/awt/Component;III)Ljavax/swing/GroupLayout$ParallelGroup;
INVOKEVIRTUAL javax/swing/GroupLayout$ParallelGroup.addGroup(Ljavax/swing/GroupLayout$Alignment;Ljavax/swing/GroupLayout$Group;)Ljavax/swing/GroupLayout$ParallelGroup;
INVOKEVIRTUAL javax/swing/GroupLayout$SequentialGroup.addGroup(Ljavax/swing/GroupLayout$Group;)Ljavax/swing/GroupLayout$SequentialGroup;
BIPUSH 6
BIPUSH 6
BIPUSH 6
INVOKEVIRTUAL javax/swing/GroupLayout$SequentialGroup.addGap(III)Ljavax/swing/GroupLayout$SequentialGroup;
INVOKEVIRTUAL javax/swing/GroupLayout$ParallelGroup.addGroup(Ljavax/swing/GroupLayout$Group;)Ljavax/swing/GroupLayout$ParallelGroup;
INVOKEVIRTUAL javax/swing/GroupLayout.setVerticalGroup(Ljavax/swing/GroupLayout$Group;)V
ALOAD 1
GETFIELD ax.b Ljavax/swing/JPanel;
NEW java/awt/Color
DUP
SIPUSH 250
SIPUSH 250
SIPUSH 250
INVOKESPECIAL java/awt/Color.<init>(III)V
INVOKEVIRTUAL javax/swing/JPanel.setBackground(Ljava/awt/Color;)V
ALOAD 1
GETFIELD ax.b Ljavax/swing/JPanel;
NEW java/awt/Color
DUP
SIPUSH 217
SIPUSH 217
SIPUSH 217
INVOKESPECIAL java/awt/Color.<init>(III)V
INVOKESTATIC javax/swing/BorderFactory.createLineBorder(Ljava/awt/Color;)Ljavax/swing/border/Border;
INVOKEVIRTUAL javax/swing/JPanel.setBorder(Ljavax/swing/border/Border;)V
NEW javax/swing/GroupLayout
DUP
ALOAD 1
GETFIELD ax.b Ljavax/swing/JPanel;
INVOKESPECIAL javax/swing/GroupLayout.<init>(Ljava/awt/Container;)V
ASTORE 2
ALOAD 1
GETFIELD ax.b Ljavax/swing/JPanel;
ALOAD 2
INVOKEVIRTUAL javax/swing/JPanel.setLayout(Ljava/awt/LayoutManager;)V
ALOAD 2
DUP
GETSTATIC javax/swing/GroupLayout$Alignment.LEADING Ljavax/swing/GroupLayout$Alignment;
INVOKEVIRTUAL javax/swing/GroupLayout.createParallelGroup(Ljavax/swing/GroupLayout$Alignment;)Ljavax/swing/GroupLayout$ParallelGroup;
ICONST_0
SIPUSH 747
SIPUSH 32767
INVOKEVIRTUAL javax/swing/GroupLayout$ParallelGroup.addGap(III)Ljavax/swing/GroupLayout$ParallelGroup;
INVOKEVIRTUAL javax/swing/GroupLayout.setHorizontalGroup(Ljavax/swing/GroupLayout$Group;)V
ALOAD 2
DUP
GETSTATIC javax/swing/GroupLayout$Alignment.LEADING Ljavax/swing/GroupLayout$Alignment;
INVOKEVIRTUAL javax/swing/GroupLayout.createParallelGroup(Ljavax/swing/GroupLayout$Alignment;)Ljavax/swing/GroupLayout$ParallelGroup;
ICONST_0
SIPUSH 538
SIPUSH 32767
INVOKEVIRTUAL javax/swing/GroupLayout$ParallelGroup.addGap(III)Ljavax/swing/GroupLayout$ParallelGroup;
INVOKEVIRTUAL javax/swing/GroupLayout.setVerticalGroup(Ljavax/swing/GroupLayout$Group;)V
ALOAD 1
GETFIELD ax.a Ljavax/swing/JPanel;
NEW java/awt/Color
DUP
SIPUSH 250
SIPUSH 250
SIPUSH 250
INVOKESPECIAL java/awt/Color.<init>(III)V
INVOKEVIRTUAL javax/swing/JPanel.setBackground(Ljava/awt/Color;)V
ALOAD 1
GETFIELD ax.a Ljavax/swing/JPanel;
NEW java/awt/Color
DUP
SIPUSH 217
SIPUSH 217
SIPUSH 217
INVOKESPECIAL java/awt/Color.<init>(III)V
INVOKESTATIC javax/swing/BorderFactory.createLineBorder(Ljava/awt/Color;)Ljavax/swing/border/Border;
INVOKEVIRTUAL javax/swing/JPanel.setBorder(Ljavax/swing/border/Border;)V
ALOAD 1
GETFIELD ax.a Ljavax/swing/JComboBox;
NEW java/awt/Color
DUP
SIPUSH 250
SIPUSH 250
SIPUSH 250
INVOKESPECIAL java/awt/Color.<init>(III)V
INVOKEVIRTUAL javax/swing/JComboBox.setBackground(Ljava/awt/Color;)V
ALOAD 1
GETFIELD ax.a Ljavax/swing/JComboBox;
NEW java/awt/Font
DUP
LDC "Dialog"
ICONST_0
BIPUSH 12
INVOKESPECIAL java/awt/Font.<init>(Ljava/lang/String;II)V
INVOKEVIRTUAL javax/swing/JComboBox.setFont(Ljava/awt/Font;)V
ALOAD 1
GETFIELD ax.a Ljavax/swing/JComboBox;
NEW java/awt/Color
DUP
BIPUSH 97
BIPUSH 97
BIPUSH 97
INVOKESPECIAL java/awt/Color.<init>(III)V
INVOKEVIRTUAL javax/swing/JComboBox.setForeground(Ljava/awt/Color;)V
ALOAD 1
GETFIELD ax.a Ljavax/swing/JComboBox;
NEW java/awt/Color
DUP
SIPUSH 250
SIPUSH 250
SIPUSH 250
INVOKESPECIAL java/awt/Color.<init>(III)V
INVOKESTATIC javax/swing/BorderFactory.createLineBorder(Ljava/awt/Color;)Ljavax/swing/border/Border;
INVOKEVIRTUAL javax/swing/JComboBox.setBorder(Ljavax/swing/border/Border;)V
ALOAD 1
GETFIELD ax.a Ljavax/swing/JComboBox;
NEW java/awt/Dimension
DUP
BIPUSH 36
BIPUSH 28
INVOKESPECIAL java/awt/Dimension.<init>(II)V
INVOKEVIRTUAL javax/swing/JComboBox.setPreferredSize(Ljava/awt/Dimension;)V
ALOAD 1
GETFIELD ax.a Ljavax/swing/JComboBox;
NEW aS
DUP
ALOAD 1
INVOKESPECIAL aS.<init>(Lax;)V
INVOKEVIRTUAL javax/swing/JComboBox.setRenderer(Ljavax/swing/ListCellRenderer;)V
ALOAD 1
GETFIELD ax.a Ljavax/swing/JComboBox;
NEW aN
DUP
ALOAD 1
INVOKESPECIAL aN.<init>(Lax;)V
INVOKEVIRTUAL javax/swing/JComboBox.addItemListener(Ljava/awt/event/ItemListener;)V
ALOAD 1
GETFIELD ax.a LcT;
LDC "SuROOT"
INVOKEVIRTUAL cT.setToolTipText(Ljava/lang/String;)V
ALOAD 1
GETFIELD ax.a LcT;
NEW aO
DUP
ALOAD 1
INVOKESPECIAL aO.<init>(Lax;)V
INVOKEVIRTUAL cT.a(LH;)V
ALOAD 1
GETFIELD ax.a LcT;
FCONST_0
INVOKEVIRTUAL cT.setAlignmentX(F)V
ALOAD 1
GETFIELD ax.a LcT;
FCONST_0
INVOKEVIRTUAL cT.setAlignmentY(F)V
ALOAD 1
GETFIELD ax.a LcT;
ICONST_1
INVOKEVIRTUAL cT.setFocusable(Z)V
ALOAD 1
GETFIELD ax.a LcT;
LDC 57566
INVOKEVIRTUAL cT.a(C)V
ALOAD 1
GETFIELD ax.d LcP;
NEW aP
DUP
ALOAD 1
INVOKESPECIAL aP.<init>(Lax;)V
INVOKEVIRTUAL cP.a(LH;)V
ALOAD 1
GETFIELD ax.d LcP;
ICONST_1
INVOKEVIRTUAL cP.setFocusable(Z)V
ALOAD 1
GETFIELD ax.d LcP;
LDC 59530
INVOKEVIRTUAL cP.a(C)V
ALOAD 1
GETFIELD ax.d LcP;
LDC "Home"
INVOKEVIRTUAL cP.a(Ljava/lang/String;)V
ALOAD 1
GETFIELD ax.b LcP;
NEW aQ
DUP
ALOAD 1
INVOKESPECIAL aQ.<init>(Lax;)V
INVOKEVIRTUAL cP.a(LH;)V
ALOAD 1
GETFIELD ax.b LcP;
ICONST_1
INVOKEVIRTUAL cP.setFocusable(Z)V
ALOAD 1
GETFIELD ax.b LcP;
LDC 58819
INVOKEVIRTUAL cP.a(C)V
ALOAD 1
GETFIELD ax.b LcP;
LDC "App Manager"
INVOKEVIRTUAL cP.a(Ljava/lang/String;)V
ALOAD 1
GETFIELD ax.a LcP;
NEW az
DUP
ALOAD 1
INVOKESPECIAL az.<init>(Lax;)V
INVOKEVIRTUAL cP.a(LH;)V
ALOAD 1
GETFIELD ax.a LcP;
ICONST_1
INVOKEVIRTUAL cP.setFocusable(Z)V
ALOAD 1
GETFIELD ax.a LcP;
LDC 57673
INVOKEVIRTUAL cP.a(C)V
ALOAD 1
GETFIELD ax.a LcP;
LDC "App Installer"
INVOKEVIRTUAL cP.a(Ljava/lang/String;)V
ALOAD 1
GETFIELD ax.c LcP;
NEW aA
DUP
ALOAD 1
INVOKESPECIAL aA.<init>(Lax;)V
INVOKEVIRTUAL cP.a(LH;)V
ALOAD 1
GETFIELD ax.c LcP;
ICONST_1
INVOKEVIRTUAL cP.setFocusable(Z)V
ALOAD 1
GETFIELD ax.c LcP;
LDC 58056
INVOKEVIRTUAL cP.a(C)V
ALOAD 1
GETFIELD ax.c LcP;
LDC "File Manager"
INVOKEVIRTUAL cP.a(Ljava/lang/String;)V
ALOAD 1
GETFIELD ax.h LcP;
NEW aB
DUP
ALOAD 1
INVOKESPECIAL aB.<init>(Lax;)V
INVOKEVIRTUAL cP.a(LH;)V
ALOAD 1
GETFIELD ax.h LcP;
ICONST_1
INVOKEVIRTUAL cP.setFocusable(Z)V
ALOAD 1
GETFIELD ax.h LcP;
LDC 58146
INVOKEVIRTUAL cP.a(C)V
ALOAD 1
GETFIELD ax.h LcP;
LDC "Tasks"
INVOKEVIRTUAL cP.a(Ljava/lang/String;)V
ALOAD 1
GETFIELD ax.f LcP;
NEW aC
DUP
ALOAD 1
INVOKESPECIAL aC.<init>(Lax;)V
INVOKEVIRTUAL cP.a(LH;)V
ALOAD 1
GETFIELD ax.f LcP;
ICONST_1
INVOKEVIRTUAL cP.setFocusable(Z)V
ALOAD 1
GETFIELD ax.f LcP;
LDC 58386
INVOKEVIRTUAL cP.a(C)V
ALOAD 1
GETFIELD ax.f LcP;
LDC "Screen Capture"
INVOKEVIRTUAL cP.a(Ljava/lang/String;)V
ALOAD 1
GETFIELD ax.e LcP;
NEW aD
DUP
ALOAD 1
INVOKESPECIAL aD.<init>(Lax;)V
INVOKEVIRTUAL cP.a(LH;)V
ALOAD 1
GETFIELD ax.e LcP;
ICONST_1
INVOKEVIRTUAL cP.setFocusable(Z)V
ALOAD 1
GETFIELD ax.e LcP;
LDC 59557
INVOKEVIRTUAL cP.a(C)V
ALOAD 1
GETFIELD ax.e LcP;
LDC "Phone Info"
INVOKEVIRTUAL cP.a(Ljava/lang/String;)V
ALOAD 1
GETFIELD ax.i LcP;
NEW aE
DUP
ALOAD 1
INVOKESPECIAL aE.<init>(Lax;)V
INVOKEVIRTUAL cP.a(LH;)V
ALOAD 1
GETFIELD ax.i LcP;
ICONST_1
INVOKEVIRTUAL cP.setFocusable(Z)V
ALOAD 1
GETFIELD ax.i LcP;
LDC 57452
INVOKEVIRTUAL cP.a(C)V
ALOAD 1
GETFIELD ax.i LcP;
LDC "Terminal"
INVOKEVIRTUAL cP.a(Ljava/lang/String;)V
ALOAD 1
GETFIELD ax.g LcP;
NEW aF
DUP
ALOAD 1
INVOKESPECIAL aF.<init>(Lax;)V
INVOKEVIRTUAL cP.a(LH;)V
ALOAD 1
GETFIELD ax.g LcP;
ICONST_1
INVOKEVIRTUAL cP.setFocusable(Z)V
ALOAD 1
GETFIELD ax.g LcP;
LDC 59576
INVOKEVIRTUAL cP.a(C)V
ALOAD 1
GETFIELD ax.g LcP;
LDC "Settings"
INVOKEVIRTUAL cP.a(Ljava/lang/String;)V
ALOAD 1
GETFIELD ax.f Ljavax/swing/JPanel;
NEW java/awt/Color
DUP
SIPUSH 250
SIPUSH 250
SIPUSH 250
INVOKESPECIAL java/awt/Color.<init>(III)V
INVOKEVIRTUAL javax/swing/JPanel.setBackground(Ljava/awt/Color;)V
ALOAD 1
GETFIELD ax.f Ljavax/swing/JPanel;
LDC "Wireless:"
INVOKESTATIC javax/swing/BorderFactory.createTitledBorder(Ljava/lang/String;)Ljavax/swing/border/TitledBorder;
INVOKEVIRTUAL javax/swing/JPanel.setBorder(Ljavax/swing/border/Border;)V
ALOAD 1
GETFIELD ax.a Ljavax/swing/JTextField;
LDC "192.168.1.1"
INVOKEVIRTUAL javax/swing/JTextField.setText(Ljava/lang/String;)V
ALOAD 1
GETFIELD ax.a Ljavax/swing/JTextField;
NEW java/awt/Dimension
DUP
BIPUSH 64
LDC 2147483647
INVOKESPECIAL java/awt/Dimension.<init>(II)V
INVOKEVIRTUAL javax/swing/JTextField.setMaximumSize(Ljava/awt/Dimension;)V
ALOAD 1
GETFIELD ax.a Ljavax/swing/JTextField;
NEW java/awt/Dimension
DUP
ICONST_4
BIPUSH 24
INVOKESPECIAL java/awt/Dimension.<init>(II)V
INVOKEVIRTUAL javax/swing/JTextField.setPreferredSize(Ljava/awt/Dimension;)V
ALOAD 1
GETFIELD ax.a Ljavax/swing/JFormattedTextField;
NEW javax/swing/text/DefaultFormatterFactory
DUP
NEW javax/swing/text/NumberFormatter
DUP
NEW java/text/DecimalFormat
DUP
LDC "#0"
INVOKESPECIAL java/text/DecimalFormat.<init>(Ljava/lang/String;)V
INVOKESPECIAL javax/swing/text/NumberFormatter.<init>(Ljava/text/NumberFormat;)V
INVOKESPECIAL javax/swing/text/DefaultFormatterFactory.<init>(Ljavax/swing/JFormattedTextField$AbstractFormatter;)V
INVOKEVIRTUAL javax/swing/JFormattedTextField.setFormatterFactory(Ljavax/swing/JFormattedTextField$AbstractFormatterFactory;)V
ALOAD 1
GETFIELD ax.a Ljavax/swing/JFormattedTextField;
LDC "5555"
INVOKEVIRTUAL javax/swing/JFormattedTextField.setText(Ljava/lang/String;)V
ALOAD 1
GETFIELD ax.a Ljavax/swing/JFormattedTextField;
NEW java/awt/Dimension
DUP
BIPUSH 64
LDC 2147483647
INVOKESPECIAL java/awt/Dimension.<init>(II)V
INVOKEVIRTUAL javax/swing/JFormattedTextField.setMaximumSize(Ljava/awt/Dimension;)V
ALOAD 1
GETFIELD ax.a Ljavax/swing/JFormattedTextField;
NEW java/awt/Dimension
DUP
ICONST_4
BIPUSH 24
INVOKESPECIAL java/awt/Dimension.<init>(II)V
INVOKEVIRTUAL javax/swing/JFormattedTextField.setPreferredSize(Ljava/awt/Dimension;)V
ALOAD 1
GETFIELD ax.a Ldc;
LDC ""
INVOKEVIRTUAL dc.setToolTipText(Ljava/lang/String;)V
ALOAD 1
GETFIELD ax.a Ldc;
NEW aG
DUP
ALOAD 1
INVOKESPECIAL aG.<init>(Lax;)V
INVOKEVIRTUAL dc.a(LH;)V
ALOAD 1
GETFIELD ax.a Ldc;
ICONST_1
INVOKEVIRTUAL dc.setFocusable(Z)V
ALOAD 1
GETFIELD ax.a Ldc;
LDC 58050
INVOKEVIRTUAL dc.a(C)V
ALOAD 1
GETFIELD ax.a Ldc;
LDC "Connect"
INVOKEVIRTUAL dc.a(Ljava/lang/String;)V
ALOAD 1
GETFIELD ax.b Ldc;
LDC ""
INVOKEVIRTUAL dc.setToolTipText(Ljava/lang/String;)V
ALOAD 1
GETFIELD ax.b Ldc;
NEW aH
DUP
ALOAD 1
INVOKESPECIAL aH.<init>(Lax;)V
INVOKEVIRTUAL dc.a(LH;)V
ALOAD 1
GETFIELD ax.b Ldc;
ICONST_1
INVOKEVIRTUAL dc.setFocusable(Z)V
ALOAD 1
GETFIELD ax.b Ldc;
LDC 58049
INVOKEVIRTUAL dc.a(C)V
ALOAD 1
GETFIELD ax.b Ldc;
LDC "Disconnect"
INVOKEVIRTUAL dc.a(Ljava/lang/String;)V
NEW javax/swing/GroupLayout
DUP
ALOAD 1
GETFIELD ax.f Ljavax/swing/JPanel;
INVOKESPECIAL javax/swing/GroupLayout.<init>(Ljava/awt/Container;)V
ASTORE 2
ALOAD 1
GETFIELD ax.f Ljavax/swing/JPanel;
ALOAD 2
INVOKEVIRTUAL javax/swing/JPanel.setLayout(Ljava/awt/LayoutManager;)V
ALOAD 2
DUP
GETSTATIC javax/swing/GroupLayout$Alignment.LEADING Ljavax/swing/GroupLayout$Alignment;
INVOKEVIRTUAL javax/swing/GroupLayout.createParallelGroup(Ljavax/swing/GroupLayout$Alignment;)Ljavax/swing/GroupLayout$ParallelGroup;
GETSTATIC javax/swing/GroupLayout$Alignment.TRAILING Ljavax/swing/GroupLayout$Alignment;
ALOAD 2
INVOKEVIRTUAL javax/swing/GroupLayout.createSequentialGroup()Ljavax/swing/GroupLayout$SequentialGroup;
ICONST_0
ICONST_0
ICONST_0
INVOKEVIRTUAL javax/swing/GroupLayout$SequentialGroup.addGap(III)Ljavax/swing/GroupLayout$SequentialGroup;
ALOAD 2
GETSTATIC javax/swing/GroupLayout$Alignment.LEADING Ljavax/swing/GroupLayout$Alignment;
INVOKEVIRTUAL javax/swing/GroupLayout.createParallelGroup(Ljavax/swing/GroupLayout$Alignment;)Ljavax/swing/GroupLayout$ParallelGroup;
ALOAD 2
INVOKEVIRTUAL javax/swing/GroupLayout.createSequentialGroup()Ljavax/swing/GroupLayout$SequentialGroup;
ALOAD 1
GETFIELD ax.a Ljavax/swing/JTextField;
ICONST_M1
ICONST_M1
SIPUSH 32767
INVOKEVIRTUAL javax/swing/GroupLayout$SequentialGroup.addComponent(Ljava/awt/Component;III)Ljavax/swing/GroupLayout$SequentialGroup;
GETSTATIC javax/swing/LayoutStyle$ComponentPlacement.RELATED Ljavax/swing/LayoutStyle$ComponentPlacement;
INVOKEVIRTUAL javax/swing/GroupLayout$SequentialGroup.addPreferredGap(Ljavax/swing/LayoutStyle$ComponentPlacement;)Ljavax/swing/GroupLayout$SequentialGroup;
ALOAD 1
GETFIELD ax.a Ljavax/swing/JFormattedTextField;
BIPUSH -2
BIPUSH 50
BIPUSH -2
INVOKEVIRTUAL javax/swing/GroupLayout$SequentialGroup.addComponent(Ljava/awt/Component;III)Ljavax/swing/GroupLayout$SequentialGroup;
INVOKEVIRTUAL javax/swing/GroupLayout$ParallelGroup.addGroup(Ljavax/swing/GroupLayout$Group;)Ljavax/swing/GroupLayout$ParallelGroup;
ALOAD 2
INVOKEVIRTUAL javax/swing/GroupLayout.createSequentialGroup()Ljavax/swing/GroupLayout$SequentialGroup;
ALOAD 1
GETFIELD ax.a Ldc;
BIPUSH -2
ICONST_M1
BIPUSH -2
INVOKEVIRTUAL javax/swing/GroupLayout$SequentialGroup.addComponent(Ljava/awt/Component;III)Ljavax/swing/GroupLayout$SequentialGroup;
GETSTATIC javax/swing/LayoutStyle$ComponentPlacement.RELATED Ljavax/swing/LayoutStyle$ComponentPlacement;
ICONST_M1
SIPUSH 32767
INVOKEVIRTUAL javax/swing/GroupLayout$SequentialGroup.addPreferredGap(Ljavax/swing/LayoutStyle$ComponentPlacement;II)Ljavax/swing/GroupLayout$SequentialGroup;
ALOAD 1
GETFIELD ax.b Ldc;
BIPUSH -2
ICONST_M1
BIPUSH -2
INVOKEVIRTUAL javax/swing/GroupLayout$SequentialGroup.addComponent(Ljava/awt/Component;III)Ljavax/swing/GroupLayout$SequentialGroup;
INVOKEVIRTUAL javax/swing/GroupLayout$ParallelGroup.addGroup(Ljavax/swing/GroupLayout$Group;)Ljavax/swing/GroupLayout$ParallelGroup;
INVOKEVIRTUAL javax/swing/GroupLayout$SequentialGroup.addGroup(Ljavax/swing/GroupLayout$Group;)Ljavax/swing/GroupLayout$SequentialGroup;
INVOKEVIRTUAL javax/swing/GroupLayout$ParallelGroup.addGroup(Ljavax/swing/GroupLayout$Alignment;Ljavax/swing/GroupLayout$Group;)Ljavax/swing/GroupLayout$ParallelGroup;
INVOKEVIRTUAL javax/swing/GroupLayout.setHorizontalGroup(Ljavax/swing/GroupLayout$Group;)V
ALOAD 2
DUP
GETSTATIC javax/swing/GroupLayout$Alignment.LEADING Ljavax/swing/GroupLayout$Alignment;
INVOKEVIRTUAL javax/swing/GroupLayout.createParallelGroup(Ljavax/swing/GroupLayout$Alignment;)Ljavax/swing/GroupLayout$ParallelGroup;
ALOAD 2
INVOKEVIRTUAL javax/swing/GroupLayout.createSequentialGroup()Ljavax/swing/GroupLayout$SequentialGroup;
ALOAD 2
GETSTATIC javax/swing/GroupLayout$Alignment.BASELINE Ljavax/swing/GroupLayout$Alignment;
INVOKEVIRTUAL javax/swing/GroupLayout.createParallelGroup(Ljavax/swing/GroupLayout$Alignment;)Ljavax/swing/GroupLayout$ParallelGroup;
ALOAD 1
GETFIELD ax.a Ljavax/swing/JTextField;
BIPUSH -2
ICONST_M1
BIPUSH -2
INVOKEVIRTUAL javax/swing/GroupLayout$ParallelGroup.addComponent(Ljava/awt/Component;III)Ljavax/swing/GroupLayout$ParallelGroup;
ALOAD 1
GETFIELD ax.a Ljavax/swing/JFormattedTextField;
BIPUSH -2
ICONST_M1
BIPUSH -2
INVOKEVIRTUAL javax/swing/GroupLayout$ParallelGroup.addComponent(Ljava/awt/Component;III)Ljavax/swing/GroupLayout$ParallelGroup;
INVOKEVIRTUAL javax/swing/GroupLayout$SequentialGroup.addGroup(Ljavax/swing/GroupLayout$Group;)Ljavax/swing/GroupLayout$SequentialGroup;
GETSTATIC javax/swing/LayoutStyle$ComponentPlacement.RELATED Ljavax/swing/LayoutStyle$ComponentPlacement;
INVOKEVIRTUAL javax/swing/GroupLayout$SequentialGroup.addPreferredGap(Ljavax/swing/LayoutStyle$ComponentPlacement;)Ljavax/swing/GroupLayout$SequentialGroup;
ALOAD 2
GETSTATIC javax/swing/GroupLayout$Alignment.LEADING Ljavax/swing/GroupLayout$Alignment;
INVOKEVIRTUAL javax/swing/GroupLayout.createParallelGroup(Ljavax/swing/GroupLayout$Alignment;)Ljavax/swing/GroupLayout$ParallelGroup;
ALOAD 1
GETFIELD ax.a Ldc;
BIPUSH -2
ICONST_M1
BIPUSH -2
INVOKEVIRTUAL javax/swing/GroupLayout$ParallelGroup.addComponent(Ljava/awt/Component;III)Ljavax/swing/GroupLayout$ParallelGroup;
ALOAD 1
GETFIELD ax.b Ldc;
BIPUSH -2
ICONST_M1
BIPUSH -2
INVOKEVIRTUAL javax/swing/GroupLayout$ParallelGroup.addComponent(Ljava/awt/Component;III)Ljavax/swing/GroupLayout$ParallelGroup;
INVOKEVIRTUAL javax/swing/GroupLayout$SequentialGroup.addGroup(Ljavax/swing/GroupLayout$Group;)Ljavax/swing/GroupLayout$SequentialGroup;
INVOKEVIRTUAL javax/swing/GroupLayout$SequentialGroup.addContainerGap()Ljavax/swing/GroupLayout$SequentialGroup;
INVOKEVIRTUAL javax/swing/GroupLayout$ParallelGroup.addGroup(Ljavax/swing/GroupLayout$Group;)Ljavax/swing/GroupLayout$ParallelGroup;
INVOKEVIRTUAL javax/swing/GroupLayout.setVerticalGroup(Ljavax/swing/GroupLayout$Group;)V
NEW javax/swing/GroupLayout
DUP
ALOAD 1
GETFIELD ax.a Ljavax/swing/JPanel;
INVOKESPECIAL javax/swing/GroupLayout.<init>(Ljava/awt/Container;)V
ASTORE 2
ALOAD 1
GETFIELD ax.a Ljavax/swing/JPanel;
ALOAD 2
INVOKEVIRTUAL javax/swing/JPanel.setLayout(Ljava/awt/LayoutManager;)V
ALOAD 2
DUP
GETSTATIC javax/swing/GroupLayout$Alignment.LEADING Ljavax/swing/GroupLayout$Alignment;
INVOKEVIRTUAL javax/swing/GroupLayout.createParallelGroup(Ljavax/swing/GroupLayout$Alignment;)Ljavax/swing/GroupLayout$ParallelGroup;
ALOAD 1
GETFIELD ax.d LcP;
GETSTATIC javax/swing/GroupLayout$Alignment.TRAILING Ljavax/swing/GroupLayout$Alignment;
BIPUSH -2
ICONST_0
SIPUSH 32767
INVOKEVIRTUAL javax/swing/GroupLayout$ParallelGroup.addComponent(Ljava/awt/Component;Ljavax/swing/GroupLayout$Alignment;III)Ljavax/swing/GroupLayout$ParallelGroup;
ALOAD 1
GETFIELD ax.b LcP;
BIPUSH -2
ICONST_0
SIPUSH 32767
INVOKEVIRTUAL javax/swing/GroupLayout$ParallelGroup.addComponent(Ljava/awt/Component;III)Ljavax/swing/GroupLayout$ParallelGroup;
ALOAD 1
GETFIELD ax.a LcP;
BIPUSH -2
ICONST_0
SIPUSH 32767
INVOKEVIRTUAL javax/swing/GroupLayout$ParallelGroup.addComponent(Ljava/awt/Component;III)Ljavax/swing/GroupLayout$ParallelGroup;
ALOAD 1
GETFIELD ax.c LcP;
BIPUSH -2
ICONST_0
SIPUSH 32767
INVOKEVIRTUAL javax/swing/GroupLayout$ParallelGroup.addComponent(Ljava/awt/Component;III)Ljavax/swing/GroupLayout$ParallelGroup;
ALOAD 1
GETFIELD ax.h LcP;
BIPUSH -2
ICONST_0
SIPUSH 32767
INVOKEVIRTUAL javax/swing/GroupLayout$ParallelGroup.addComponent(Ljava/awt/Component;III)Ljavax/swing/GroupLayout$ParallelGroup;
ALOAD 1
GETFIELD ax.f LcP;
BIPUSH -2
ICONST_0
SIPUSH 32767
INVOKEVIRTUAL javax/swing/GroupLayout$ParallelGroup.addComponent(Ljava/awt/Component;III)Ljavax/swing/GroupLayout$ParallelGroup;
ALOAD 1
GETFIELD ax.e LcP;
BIPUSH -2
ICONST_0
SIPUSH 32767
INVOKEVIRTUAL javax/swing/GroupLayout$ParallelGroup.addComponent(Ljava/awt/Component;III)Ljavax/swing/GroupLayout$ParallelGroup;
ALOAD 1
GETFIELD ax.i LcP;
BIPUSH -2
ICONST_0
SIPUSH 32767
INVOKEVIRTUAL javax/swing/GroupLayout$ParallelGroup.addComponent(Ljava/awt/Component;III)Ljavax/swing/GroupLayout$ParallelGroup;
ALOAD 1
GETFIELD ax.g LcP;
BIPUSH -2
ICONST_0
SIPUSH 32767
INVOKEVIRTUAL javax/swing/GroupLayout$ParallelGroup.addComponent(Ljava/awt/Component;III)Ljavax/swing/GroupLayout$ParallelGroup;
ALOAD 2
INVOKEVIRTUAL javax/swing/GroupLayout.createSequentialGroup()Ljavax/swing/GroupLayout$SequentialGroup;
ALOAD 1
GETFIELD ax.a Ljavax/swing/JComboBox;
ICONST_0
ICONST_M1
SIPUSH 32767
INVOKEVIRTUAL javax/swing/GroupLayout$SequentialGroup.addComponent(Ljava/awt/Component;III)Ljavax/swing/GroupLayout$SequentialGroup;
ICONST_0
ICONST_0
ICONST_0
INVOKEVIRTUAL javax/swing/GroupLayout$SequentialGroup.addGap(III)Ljavax/swing/GroupLayout$SequentialGroup;
ALOAD 1
GETFIELD ax.a LcT;
BIPUSH -2
ICONST_M1
BIPUSH -2
INVOKEVIRTUAL javax/swing/GroupLayout$SequentialGroup.addComponent(Ljava/awt/Component;III)Ljavax/swing/GroupLayout$SequentialGroup;
INVOKEVIRTUAL javax/swing/GroupLayout$ParallelGroup.addGroup(Ljavax/swing/GroupLayout$Group;)Ljavax/swing/GroupLayout$ParallelGroup;
ALOAD 1
GETFIELD ax.f Ljavax/swing/JPanel;
ICONST_M1
ICONST_M1
SIPUSH 32767
INVOKEVIRTUAL javax/swing/GroupLayout$ParallelGroup.addComponent(Ljava/awt/Component;III)Ljavax/swing/GroupLayout$ParallelGroup;
INVOKEVIRTUAL javax/swing/GroupLayout.setHorizontalGroup(Ljavax/swing/GroupLayout$Group;)V
ALOAD 2
DUP
GETSTATIC javax/swing/GroupLayout$Alignment.LEADING Ljavax/swing/GroupLayout$Alignment;
INVOKEVIRTUAL javax/swing/GroupLayout.createParallelGroup(Ljavax/swing/GroupLayout$Alignment;)Ljavax/swing/GroupLayout$ParallelGroup;
ALOAD 2
INVOKEVIRTUAL javax/swing/GroupLayout.createSequentialGroup()Ljavax/swing/GroupLayout$SequentialGroup;
ALOAD 2
GETSTATIC javax/swing/GroupLayout$Alignment.LEADING Ljavax/swing/GroupLayout$Alignment;
ICONST_0
INVOKEVIRTUAL javax/swing/GroupLayout.createParallelGroup(Ljavax/swing/GroupLayout$Alignment;Z)Ljavax/swing/GroupLayout$ParallelGroup;
ALOAD 1
GETFIELD ax.a Ljavax/swing/JComboBox;
ICONST_M1
BIPUSH 54
SIPUSH 32767
INVOKEVIRTUAL javax/swing/GroupLayout$ParallelGroup.addComponent(Ljava/awt/Component;III)Ljavax/swing/GroupLayout$ParallelGroup;
ALOAD 1
GETFIELD ax.a LcT;
ICONST_M1
ICONST_M1
SIPUSH 32767
INVOKEVIRTUAL javax/swing/GroupLayout$ParallelGroup.addComponent(Ljava/awt/Component;III)Ljavax/swing/GroupLayout$ParallelGroup;
INVOKEVIRTUAL javax/swing/GroupLayout$SequentialGroup.addGroup(Ljavax/swing/GroupLayout$Group;)Ljavax/swing/GroupLayout$SequentialGroup;
GETSTATIC javax/swing/LayoutStyle$ComponentPlacement.RELATED Ljavax/swing/LayoutStyle$ComponentPlacement;
INVOKEVIRTUAL javax/swing/GroupLayout$SequentialGroup.addPreferredGap(Ljavax/swing/LayoutStyle$ComponentPlacement;)Ljavax/swing/GroupLayout$SequentialGroup;
ALOAD 1
GETFIELD ax.f Ljavax/swing/JPanel;
BIPUSH -2
ICONST_M1
BIPUSH -2
INVOKEVIRTUAL javax/swing/GroupLayout$SequentialGroup.addComponent(Ljava/awt/Component;III)Ljavax/swing/GroupLayout$SequentialGroup;
GETSTATIC javax/swing/LayoutStyle$ComponentPlacement.RELATED Ljavax/swing/LayoutStyle$ComponentPlacement;
INVOKEVIRTUAL javax/swing/GroupLayout$SequentialGroup.addPreferredGap(Ljavax/swing/LayoutStyle$ComponentPlacement;)Ljavax/swing/GroupLayout$SequentialGroup;
ALOAD 1
GETFIELD ax.d LcP;
BIPUSH -2
BIPUSH 32
BIPUSH -2
INVOKEVIRTUAL javax/swing/GroupLayout$SequentialGroup.addComponent(Ljava/awt/Component;III)Ljavax/swing/GroupLayout$SequentialGroup;
ICONST_0
ICONST_0
ICONST_0
INVOKEVIRTUAL javax/swing/GroupLayout$SequentialGroup.addGap(III)Ljavax/swing/GroupLayout$SequentialGroup;
ALOAD 1
GETFIELD ax.a LcP;
BIPUSH -2
BIPUSH 32
BIPUSH -2
INVOKEVIRTUAL javax/swing/GroupLayout$SequentialGroup.addComponent(Ljava/awt/Component;III)Ljavax/swing/GroupLayout$SequentialGroup;
ICONST_0
ICONST_0
ICONST_0
INVOKEVIRTUAL javax/swing/GroupLayout$SequentialGroup.addGap(III)Ljavax/swing/GroupLayout$SequentialGroup;
ALOAD 1
GETFIELD ax.b LcP;
BIPUSH -2
BIPUSH 32
BIPUSH -2
INVOKEVIRTUAL javax/swing/GroupLayout$SequentialGroup.addComponent(Ljava/awt/Component;III)Ljavax/swing/GroupLayout$SequentialGroup;
ICONST_0
ICONST_0
ICONST_0
INVOKEVIRTUAL javax/swing/GroupLayout$SequentialGroup.addGap(III)Ljavax/swing/GroupLayout$SequentialGroup;
ALOAD 1
GETFIELD ax.c LcP;
BIPUSH -2
BIPUSH 32
BIPUSH -2
INVOKEVIRTUAL javax/swing/GroupLayout$SequentialGroup.addComponent(Ljava/awt/Component;III)Ljavax/swing/GroupLayout$SequentialGroup;
ICONST_0
ICONST_0
ICONST_0
INVOKEVIRTUAL javax/swing/GroupLayout$SequentialGroup.addGap(III)Ljavax/swing/GroupLayout$SequentialGroup;
ALOAD 1
GETFIELD ax.f LcP;
BIPUSH -2
BIPUSH 32
BIPUSH -2
INVOKEVIRTUAL javax/swing/GroupLayout$SequentialGroup.addComponent(Ljava/awt/Component;III)Ljavax/swing/GroupLayout$SequentialGroup;
ICONST_0
ICONST_0
ICONST_0
INVOKEVIRTUAL javax/swing/GroupLayout$SequentialGroup.addGap(III)Ljavax/swing/GroupLayout$SequentialGroup;
ALOAD 1
GETFIELD ax.e LcP;
BIPUSH -2
BIPUSH 32
BIPUSH -2
INVOKEVIRTUAL javax/swing/GroupLayout$SequentialGroup.addComponent(Ljava/awt/Component;III)Ljavax/swing/GroupLayout$SequentialGroup;
ICONST_0
ICONST_0
ICONST_0
INVOKEVIRTUAL javax/swing/GroupLayout$SequentialGroup.addGap(III)Ljavax/swing/GroupLayout$SequentialGroup;
ALOAD 1
GETFIELD ax.i LcP;
BIPUSH -2
BIPUSH 32
BIPUSH -2
INVOKEVIRTUAL javax/swing/GroupLayout$SequentialGroup.addComponent(Ljava/awt/Component;III)Ljavax/swing/GroupLayout$SequentialGroup;
BIPUSH 63
BIPUSH 63
BIPUSH 63
INVOKEVIRTUAL javax/swing/GroupLayout$SequentialGroup.addGap(III)Ljavax/swing/GroupLayout$SequentialGroup;
ALOAD 1
GETFIELD ax.g LcP;
BIPUSH -2
BIPUSH 32
BIPUSH -2
INVOKEVIRTUAL javax/swing/GroupLayout$SequentialGroup.addComponent(Ljava/awt/Component;III)Ljavax/swing/GroupLayout$SequentialGroup;
GETSTATIC javax/swing/LayoutStyle$ComponentPlacement.RELATED Ljavax/swing/LayoutStyle$ComponentPlacement;
ICONST_M1
SIPUSH 32767
INVOKEVIRTUAL javax/swing/GroupLayout$SequentialGroup.addPreferredGap(Ljavax/swing/LayoutStyle$ComponentPlacement;II)Ljavax/swing/GroupLayout$SequentialGroup;
ALOAD 1
GETFIELD ax.h LcP;
BIPUSH -2
BIPUSH 32
BIPUSH -2
INVOKEVIRTUAL javax/swing/GroupLayout$SequentialGroup.addComponent(Ljava/awt/Component;III)Ljavax/swing/GroupLayout$SequentialGroup;
INVOKEVIRTUAL javax/swing/GroupLayout$ParallelGroup.addGroup(Ljavax/swing/GroupLayout$Group;)Ljavax/swing/GroupLayout$ParallelGroup;
INVOKEVIRTUAL javax/swing/GroupLayout.setVerticalGroup(Ljavax/swing/GroupLayout$Group;)V
ALOAD 1
GETFIELD ax.d Ljavax/swing/JPanel;
NEW java/awt/Color
DUP
SIPUSH 250
SIPUSH 250
SIPUSH 250
INVOKESPECIAL java/awt/Color.<init>(III)V
INVOKEVIRTUAL javax/swing/JPanel.setBackground(Ljava/awt/Color;)V
ALOAD 1
GETFIELD ax.d Ljavax/swing/JPanel;
NEW java/awt/Color
DUP
SIPUSH 217
SIPUSH 217
SIPUSH 217
INVOKESPECIAL java/awt/Color.<init>(III)V
INVOKESTATIC javax/swing/BorderFactory.createLineBorder(Ljava/awt/Color;)Ljavax/swing/border/Border;
INVOKEVIRTUAL javax/swing/JPanel.setBorder(Ljavax/swing/border/Border;)V
ALOAD 1
GETFIELD ax.d Ljavax/swing/JPanel;
NEW java/awt/Dimension
DUP
BIPUSH 100
BIPUSH 32
INVOKESPECIAL java/awt/Dimension.<init>(II)V
INVOKEVIRTUAL javax/swing/JPanel.setMinimumSize(Ljava/awt/Dimension;)V
ALOAD 1
GETFIELD ax.d Ljavax/swing/JPanel;
NEW java/awt/Dimension
DUP
SIPUSH 137
BIPUSH 32
INVOKESPECIAL java/awt/Dimension.<init>(II)V
INVOKEVIRTUAL javax/swing/JPanel.setPreferredSize(Ljava/awt/Dimension;)V
ALOAD 1
GETFIELD ax.a Ljavax/swing/JLabel;
NEW java/awt/Font
DUP
LDC "Dialog"
ICONST_1
BIPUSH 10
INVOKESPECIAL java/awt/Font.<init>(Ljava/lang/String;II)V
INVOKEVIRTUAL javax/swing/JLabel.setFont(Ljava/awt/Font;)V
ALOAD 1
GETFIELD ax.a Ljavax/swing/JLabel;
NEW java/awt/Color
DUP
BIPUSH 97
BIPUSH 97
BIPUSH 97
INVOKESPECIAL java/awt/Color.<init>(III)V
INVOKEVIRTUAL javax/swing/JLabel.setForeground(Ljava/awt/Color;)V
ALOAD 1
GETFIELD ax.a Ljavax/swing/JLabel;
ICONST_4
INVOKEVIRTUAL javax/swing/JLabel.setHorizontalAlignment(I)V
ALOAD 1
GETFIELD ax.a Ljavax/swing/JSeparator;
NEW java/awt/Color
DUP
SIPUSH 250
SIPUSH 250
SIPUSH 250
INVOKESPECIAL java/awt/Color.<init>(III)V
INVOKEVIRTUAL javax/swing/JSeparator.setBackground(Ljava/awt/Color;)V
ALOAD 1
GETFIELD ax.a Ljavax/swing/JSeparator;
NEW java/awt/Color
DUP
SIPUSH 217
SIPUSH 217
SIPUSH 217
INVOKESPECIAL java/awt/Color.<init>(III)V
INVOKEVIRTUAL javax/swing/JSeparator.setForeground(Ljava/awt/Color;)V
ALOAD 1
GETFIELD ax.a Ljavax/swing/JSeparator;
ICONST_1
INVOKEVIRTUAL javax/swing/JSeparator.setOrientation(I)V
ALOAD 1
GETFIELD ax.a Ljavax/swing/JProgressBar;
NEW java/awt/Color
DUP
BIPUSH 76
SIPUSH 175
BIPUSH 80
INVOKESPECIAL java/awt/Color.<init>(III)V
INVOKEVIRTUAL javax/swing/JProgressBar.setForeground(Ljava/awt/Color;)V
ALOAD 1
GETFIELD ax.a Ljavax/swing/JProgressBar;
LDC ""
INVOKEVIRTUAL javax/swing/JProgressBar.setToolTipText(Ljava/lang/String;)V
ALOAD 1
GETFIELD ax.a Ljavax/swing/JProgressBar;
ICONST_1
INVOKEVIRTUAL javax/swing/JProgressBar.setStringPainted(Z)V
ALOAD 1
GETFIELD ax.a Ljavax/swing/JProgressBar;
NEW aI
DUP
ALOAD 1
INVOKESPECIAL aI.<init>(Lax;)V
INVOKEVIRTUAL javax/swing/JProgressBar.addMouseListener(Ljava/awt/event/MouseListener;)V
ALOAD 1
GETFIELD ax.c Ljavax/swing/JLabel;
NEW java/awt/Font
DUP
LDC "Dialog"
ICONST_0
BIPUSH 12
INVOKESPECIAL java/awt/Font.<init>(Ljava/lang/String;II)V
INVOKEVIRTUAL javax/swing/JLabel.setFont(Ljava/awt/Font;)V
ALOAD 1
GETFIELD ax.c Ljavax/swing/JLabel;
NEW java/awt/Color
DUP
BIPUSH 97
BIPUSH 97
BIPUSH 97
INVOKESPECIAL java/awt/Color.<init>(III)V
INVOKEVIRTUAL javax/swing/JLabel.setForeground(Ljava/awt/Color;)V
ALOAD 1
GETFIELD ax.c Ljavax/swing/JLabel;
ICONST_4
INVOKEVIRTUAL javax/swing/JLabel.setHorizontalAlignment(I)V
NEW javax/swing/GroupLayout
DUP
ALOAD 1
GETFIELD ax.d Ljavax/swing/JPanel;
INVOKESPECIAL javax/swing/GroupLayout.<init>(Ljava/awt/Container;)V
ASTORE 2
ALOAD 1
GETFIELD ax.d Ljavax/swing/JPanel;
ALOAD 2
INVOKEVIRTUAL javax/swing/JPanel.setLayout(Ljava/awt/LayoutManager;)V
ALOAD 2
DUP
GETSTATIC javax/swing/GroupLayout$Alignment.LEADING Ljavax/swing/GroupLayout$Alignment;
INVOKEVIRTUAL javax/swing/GroupLayout.createParallelGroup(Ljavax/swing/GroupLayout$Alignment;)Ljavax/swing/GroupLayout$ParallelGroup;
GETSTATIC javax/swing/GroupLayout$Alignment.TRAILING Ljavax/swing/GroupLayout$Alignment;
ALOAD 2
INVOKEVIRTUAL javax/swing/GroupLayout.createSequentialGroup()Ljavax/swing/GroupLayout$SequentialGroup;
ALOAD 1
GETFIELD ax.a Ljavax/swing/JProgressBar;
BIPUSH -2
SIPUSH 198
BIPUSH -2
INVOKEVIRTUAL javax/swing/GroupLayout$SequentialGroup.addComponent(Ljava/awt/Component;III)Ljavax/swing/GroupLayout$SequentialGroup;
BIPUSH 6
BIPUSH 6
BIPUSH 6
INVOKEVIRTUAL javax/swing/GroupLayout$SequentialGroup.addGap(III)Ljavax/swing/GroupLayout$SequentialGroup;
ALOAD 1
GETFIELD ax.c Ljavax/swing/JLabel;
ICONST_M1
SIPUSH 592
SIPUSH 32767
INVOKEVIRTUAL javax/swing/GroupLayout$SequentialGroup.addComponent(Ljava/awt/Component;III)Ljavax/swing/GroupLayout$SequentialGroup;
BIPUSH 6
BIPUSH 6
BIPUSH 6
INVOKEVIRTUAL javax/swing/GroupLayout$SequentialGroup.addGap(III)Ljavax/swing/GroupLayout$SequentialGroup;
ALOAD 1
GETFIELD ax.a Ljavax/swing/JSeparator;
BIPUSH -2
BIPUSH 6
BIPUSH -2
INVOKEVIRTUAL javax/swing/GroupLayout$SequentialGroup.addComponent(Ljava/awt/Component;III)Ljavax/swing/GroupLayout$SequentialGroup;
ICONST_0
ICONST_0
ICONST_0
INVOKEVIRTUAL javax/swing/GroupLayout$SequentialGroup.addGap(III)Ljavax/swing/GroupLayout$SequentialGroup;
ALOAD 1
GETFIELD ax.a Ljavax/swing/JLabel;
BIPUSH -2
SIPUSH 128
BIPUSH -2
INVOKEVIRTUAL javax/swing/GroupLayout$SequentialGroup.addComponent(Ljava/awt/Component;III)Ljavax/swing/GroupLayout$SequentialGroup;
BIPUSH 6
BIPUSH 6
BIPUSH 6
INVOKEVIRTUAL javax/swing/GroupLayout$SequentialGroup.addGap(III)Ljavax/swing/GroupLayout$SequentialGroup;
INVOKEVIRTUAL javax/swing/GroupLayout$ParallelGroup.addGroup(Ljavax/swing/GroupLayout$Alignment;Ljavax/swing/GroupLayout$Group;)Ljavax/swing/GroupLayout$ParallelGroup;
INVOKEVIRTUAL javax/swing/GroupLayout.setHorizontalGroup(Ljavax/swing/GroupLayout$Group;)V
ALOAD 2
DUP
GETSTATIC javax/swing/GroupLayout$Alignment.LEADING Ljavax/swing/GroupLayout$Alignment;
INVOKEVIRTUAL javax/swing/GroupLayout.createParallelGroup(Ljavax/swing/GroupLayout$Alignment;)Ljavax/swing/GroupLayout$ParallelGroup;
ALOAD 1
GETFIELD ax.a Ljavax/swing/JSeparator;
INVOKEVIRTUAL javax/swing/GroupLayout$ParallelGroup.addComponent(Ljava/awt/Component;)Ljavax/swing/GroupLayout$ParallelGroup;
ALOAD 1
GETFIELD ax.a Ljavax/swing/JLabel;
GETSTATIC javax/swing/GroupLayout$Alignment.TRAILING Ljavax/swing/GroupLayout$Alignment;
ICONST_M1
ICONST_M1
SIPUSH 32767
INVOKEVIRTUAL javax/swing/GroupLayout$ParallelGroup.addComponent(Ljava/awt/Component;Ljavax/swing/GroupLayout$Alignment;III)Ljavax/swing/GroupLayout$ParallelGroup;
ALOAD 1
GETFIELD ax.a Ljavax/swing/JProgressBar;
GETSTATIC javax/swing/GroupLayout$Alignment.TRAILING Ljavax/swing/GroupLayout$Alignment;
ICONST_M1
BIPUSH 30
SIPUSH 32767
INVOKEVIRTUAL javax/swing/GroupLayout$ParallelGroup.addComponent(Ljava/awt/Component;Ljavax/swing/GroupLayout$Alignment;III)Ljavax/swing/GroupLayout$ParallelGroup;
ALOAD 1
GETFIELD ax.c Ljavax/swing/JLabel;
GETSTATIC javax/swing/GroupLayout$Alignment.TRAILING Ljavax/swing/GroupLayout$Alignment;
ICONST_M1
ICONST_M1
SIPUSH 32767
INVOKEVIRTUAL javax/swing/GroupLayout$ParallelGroup.addComponent(Ljava/awt/Component;Ljavax/swing/GroupLayout$Alignment;III)Ljavax/swing/GroupLayout$ParallelGroup;
INVOKEVIRTUAL javax/swing/GroupLayout.setVerticalGroup(Ljavax/swing/GroupLayout$Group;)V
NEW javax/swing/GroupLayout
DUP
ALOAD 1
GETFIELD ax.c Ljavax/swing/JPanel;
INVOKESPECIAL javax/swing/GroupLayout.<init>(Ljava/awt/Container;)V
ASTORE 2
ALOAD 1
GETFIELD ax.c Ljavax/swing/JPanel;
ALOAD 2
INVOKEVIRTUAL javax/swing/JPanel.setLayout(Ljava/awt/LayoutManager;)V
ALOAD 2
DUP
GETSTATIC javax/swing/GroupLayout$Alignment.LEADING Ljavax/swing/GroupLayout$Alignment;
INVOKEVIRTUAL javax/swing/GroupLayout.createParallelGroup(Ljavax/swing/GroupLayout$Alignment;)Ljavax/swing/GroupLayout$ParallelGroup;
ALOAD 1
GETFIELD ax.e Ljavax/swing/JPanel;
ICONST_M1
ICONST_M1
SIPUSH 32767
INVOKEVIRTUAL javax/swing/GroupLayout$ParallelGroup.addComponent(Ljava/awt/Component;III)Ljavax/swing/GroupLayout$ParallelGroup;
ALOAD 2
INVOKEVIRTUAL javax/swing/GroupLayout.createSequentialGroup()Ljavax/swing/GroupLayout$SequentialGroup;
ALOAD 1
GETFIELD ax.a Ljavax/swing/JPanel;
BIPUSH -2
ICONST_M1
BIPUSH -2
INVOKEVIRTUAL javax/swing/GroupLayout$SequentialGroup.addComponent(Ljava/awt/Component;III)Ljavax/swing/GroupLayout$SequentialGroup;
ICONST_0
ICONST_0
ICONST_0
INVOKEVIRTUAL javax/swing/GroupLayout$SequentialGroup.addGap(III)Ljavax/swing/GroupLayout$SequentialGroup;
ALOAD 1
GETFIELD ax.b Ljavax/swing/JPanel;
ICONST_M1
ICONST_M1
SIPUSH 32767
INVOKEVIRTUAL javax/swing/GroupLayout$SequentialGroup.addComponent(Ljava/awt/Component;III)Ljavax/swing/GroupLayout$SequentialGroup;
INVOKEVIRTUAL javax/swing/GroupLayout$ParallelGroup.addGroup(Ljavax/swing/GroupLayout$Group;)Ljavax/swing/GroupLayout$ParallelGroup;
ALOAD 1
GETFIELD ax.d Ljavax/swing/JPanel;
ICONST_M1
SIPUSH 944
SIPUSH 32767
INVOKEVIRTUAL javax/swing/GroupLayout$ParallelGroup.addComponent(Ljava/awt/Component;III)Ljavax/swing/GroupLayout$ParallelGroup;
INVOKEVIRTUAL javax/swing/GroupLayout.setHorizontalGroup(Ljavax/swing/GroupLayout$Group;)V
ALOAD 2
DUP
GETSTATIC javax/swing/GroupLayout$Alignment.LEADING Ljavax/swing/GroupLayout$Alignment;
INVOKEVIRTUAL javax/swing/GroupLayout.createParallelGroup(Ljavax/swing/GroupLayout$Alignment;)Ljavax/swing/GroupLayout$ParallelGroup;
ALOAD 2
INVOKEVIRTUAL javax/swing/GroupLayout.createSequentialGroup()Ljavax/swing/GroupLayout$SequentialGroup;
ICONST_0
ICONST_0
ICONST_0
INVOKEVIRTUAL javax/swing/GroupLayout$SequentialGroup.addGap(III)Ljavax/swing/GroupLayout$SequentialGroup;
ALOAD 1
GETFIELD ax.e Ljavax/swing/JPanel;
BIPUSH -2
ICONST_M1
BIPUSH -2
INVOKEVIRTUAL javax/swing/GroupLayout$SequentialGroup.addComponent(Ljava/awt/Component;III)Ljavax/swing/GroupLayout$SequentialGroup;
ICONST_0
ICONST_0
ICONST_0
INVOKEVIRTUAL javax/swing/GroupLayout$SequentialGroup.addGap(III)Ljavax/swing/GroupLayout$SequentialGroup;
ALOAD 2
GETSTATIC javax/swing/GroupLayout$Alignment.LEADING Ljavax/swing/GroupLayout$Alignment;
INVOKEVIRTUAL javax/swing/GroupLayout.createParallelGroup(Ljavax/swing/GroupLayout$Alignment;)Ljavax/swing/GroupLayout$ParallelGroup;
ALOAD 1
GETFIELD ax.b Ljavax/swing/JPanel;
ICONST_M1
ICONST_M1
SIPUSH 32767
INVOKEVIRTUAL javax/swing/GroupLayout$ParallelGroup.addComponent(Ljava/awt/Component;III)Ljavax/swing/GroupLayout$ParallelGroup;
ALOAD 1
GETFIELD ax.a Ljavax/swing/JPanel;
ICONST_M1
ICONST_M1
SIPUSH 32767
INVOKEVIRTUAL javax/swing/GroupLayout$ParallelGroup.addComponent(Ljava/awt/Component;III)Ljavax/swing/GroupLayout$ParallelGroup;
INVOKEVIRTUAL javax/swing/GroupLayout$SequentialGroup.addGroup(Ljavax/swing/GroupLayout$Group;)Ljavax/swing/GroupLayout$SequentialGroup;
ICONST_0
ICONST_0
ICONST_0
INVOKEVIRTUAL javax/swing/GroupLayout$SequentialGroup.addGap(III)Ljavax/swing/GroupLayout$SequentialGroup;
ALOAD 1
GETFIELD ax.d Ljavax/swing/JPanel;
BIPUSH -2
ICONST_M1
BIPUSH -2
INVOKEVIRTUAL javax/swing/GroupLayout$SequentialGroup.addComponent(Ljava/awt/Component;III)Ljavax/swing/GroupLayout$SequentialGroup;
INVOKEVIRTUAL javax/swing/GroupLayout$ParallelGroup.addGroup(Ljavax/swing/GroupLayout$Group;)Ljavax/swing/GroupLayout$ParallelGroup;
INVOKEVIRTUAL javax/swing/GroupLayout.setVerticalGroup(Ljavax/swing/GroupLayout$Group;)V
NEW javax/swing/GroupLayout
DUP
ALOAD 1
INVOKEVIRTUAL ax.getContentPane()Ljava/awt/Container;
INVOKESPECIAL javax/swing/GroupLayout.<init>(Ljava/awt/Container;)V
ASTORE 2
ALOAD 1
INVOKEVIRTUAL ax.getContentPane()Ljava/awt/Container;
ALOAD 2
INVOKEVIRTUAL java/awt/Container.setLayout(Ljava/awt/LayoutManager;)V
ALOAD 2
DUP
GETSTATIC javax/swing/GroupLayout$Alignment.LEADING Ljavax/swing/GroupLayout$Alignment;
INVOKEVIRTUAL javax/swing/GroupLayout.createParallelGroup(Ljavax/swing/GroupLayout$Alignment;)Ljavax/swing/GroupLayout$ParallelGroup;
ALOAD 2
INVOKEVIRTUAL javax/swing/GroupLayout.createSequentialGroup()Ljavax/swing/GroupLayout$SequentialGroup;
ICONST_0
ICONST_0
ICONST_0
INVOKEVIRTUAL javax/swing/GroupLayout$SequentialGroup.addGap(III)Ljavax/swing/GroupLayout$SequentialGroup;
ALOAD 1
GETFIELD ax.c Ljavax/swing/JPanel;
ICONST_M1
ICONST_M1
SIPUSH 32767
INVOKEVIRTUAL javax/swing/GroupLayout$SequentialGroup.addComponent(Ljava/awt/Component;III)Ljavax/swing/GroupLayout$SequentialGroup;
INVOKEVIRTUAL javax/swing/GroupLayout$ParallelGroup.addGroup(Ljavax/swing/GroupLayout$Group;)Ljavax/swing/GroupLayout$ParallelGroup;
INVOKEVIRTUAL javax/swing/GroupLayout.setHorizontalGroup(Ljavax/swing/GroupLayout$Group;)V
ALOAD 2
DUP
GETSTATIC javax/swing/GroupLayout$Alignment.LEADING Ljavax/swing/GroupLayout$Alignment;
INVOKEVIRTUAL javax/swing/GroupLayout.createParallelGroup(Ljavax/swing/GroupLayout$Alignment;)Ljavax/swing/GroupLayout$ParallelGroup;
ALOAD 1
GETFIELD ax.c Ljavax/swing/JPanel;
ICONST_M1
ICONST_M1
SIPUSH 32767
INVOKEVIRTUAL javax/swing/GroupLayout$ParallelGroup.addComponent(Ljava/awt/Component;III)Ljavax/swing/GroupLayout$ParallelGroup;
INVOKEVIRTUAL javax/swing/GroupLayout.setVerticalGroup(Ljavax/swing/GroupLayout$Group;)V
ALOAD 1
INVOKEVIRTUAL ax.pack()V
ALOAD this
GETFIELD ax.a Ljavax/swing/JButton;
ALOAD this
GETFIELD ax.a LaR;
INVOKEVIRTUAL javax/swing/JButton.addMouseListener(Ljava/awt/event/MouseListener;)V
ALOAD this
GETFIELD ax.c Ljavax/swing/JButton;
ALOAD this
GETFIELD ax.a LaR;
INVOKEVIRTUAL javax/swing/JButton.addMouseListener(Ljava/awt/event/MouseListener;)V
ALOAD this
GETFIELD ax.b Ljavax/swing/JButton;
ALOAD this
GETFIELD ax.a LaR;
INVOKEVIRTUAL javax/swing/JButton.addMouseListener(Ljava/awt/event/MouseListener;)V
NEW aT
DUP
ALOAD this
INVOKESPECIAL aT.<init>(Lax;)V
ASTORE 1
ALOAD this
ALOAD 1
INVOKEVIRTUAL ax.addMouseListener(Ljava/awt/event/MouseListener;)V
ALOAD this
ALOAD 1
INVOKEVIRTUAL ax.addMouseMotionListener(Ljava/awt/event/MouseMotionListener;)V
ALOAD this
INVOKESPECIAL ax.c()V
ALOAD this
INVOKESPECIAL ax.d()V
ALOAD this
NEW ay
DUP
ALOAD this
INVOKESPECIAL ay.<init>(Lax;)V
PUTFIELD ax.a LH;
ALOAD this
INVOKESPECIAL ax.e()V
NEW javax/swing/Timer
DUP
SIPUSH 1000
ALOAD this
INVOKEDYNAMIC actionPerformed (Lax;)Ljava/awt/event/ActionListener; ${H_META} args[(Ljava/awt/event/ActionEvent;)V, handle[H_INVOKESPECIAL ax.a(Ljava/awt/event/ActionEvent;)V], (Ljava/awt/event/ActionEvent;)V]
INVOKESPECIAL javax/swing/Timer.<init>(ILjava/awt/event/ActionListener;)V
INVOKEVIRTUAL javax/swing/Timer.start()V
LDC "Expert_Settings"
INVOKESTATIC ac.a(Ljava/lang/String;)Ljava/lang/String;
INVOKESTATIC java/lang/Boolean.valueOf(Ljava/lang/String;)Ljava/lang/Boolean;
INVOKEVIRTUAL java/lang/Boolean.booleanValue()Z
IFNE B
ALOAD this
GETFIELD ax.i LcP;
ICONST_0
INVOKEVIRTUAL cP.setVisible(Z)V
B:
LDC "SuRoot"
INVOKESTATIC ac.a(Ljava/lang/String;)Ljava/lang/String;
INVOKESTATIC java/lang/Boolean.valueOf(Ljava/lang/String;)Ljava/lang/Boolean;
INVOKEVIRTUAL java/lang/Boolean.booleanValue()Z
IFNE C
ALOAD this
GETFIELD ax.a LcT;
ICONST_0
INVOKEVIRTUAL cT.setVisible(Z)V
C:
ALOAD this
INVOKESPECIAL ax.f()V
RETURN
D:
E: