DEFINE PUBLIC <init>()V
ALIAS H_META "handle[H_INVOKESTATIC java/lang/invoke/LambdaMetafactory.metafactory(Ljava/lang/invoke/MethodHandles$Lookup;Ljava/lang/String;Ljava/lang/invoke/MethodType;Ljava/lang/invoke/MethodType;Ljava/lang/invoke/MethodHandle;Ljava/lang/invoke/MethodType;)Ljava/lang/invoke/CallSite;]"
A:
ALOAD this
INVOKESPECIAL javax/swing/JFrame.<init>()V
ALOAD this
NEW cp
DUP
INVOKESPECIAL cp.<init>()V
PUTFIELD az.a Lcp;
ALOAD this
NEW cz
DUP
INVOKESPECIAL cz.<init>()V
PUTFIELD az.a Lcz;
ALOAD this
NEW cw
DUP
INVOKESPECIAL cw.<init>()V
PUTFIELD az.a Lcw;
ALOAD this
NEW bp
DUP
INVOKESPECIAL bp.<init>()V
PUTFIELD az.a Lbp;
ALOAD this
NEW aY
DUP
INVOKESPECIAL aY.<init>()V
PUTFIELD az.a LaY;
ALOAD this
NEW cj
DUP
INVOKESPECIAL cj.<init>()V
PUTFIELD az.a Lcj;
ALOAD this
NEW cq
DUP
INVOKESPECIAL cq.<init>()V
PUTFIELD az.a Lcq;
ALOAD this
NEW bM
DUP
INVOKESPECIAL bM.<init>()V
PUTFIELD az.a LbM;
ALOAD this
NEW cQ
DUP
INVOKESPECIAL cQ.<init>()V
PUTFIELD az.a LcQ;
ALOAD this
NEW aU
DUP
ALOAD this
ICONST_0
INVOKESPECIAL aU.<init>(Laz;B)V
PUTFIELD az.a LaU;
ALOAD this
NEW java/util/ArrayList
DUP
INVOKESPECIAL java/util/ArrayList.<init>()V
PUTFIELD az.a Ljava/util/List;
ALOAD this
NEW java/util/ArrayList
DUP
INVOKESPECIAL java/util/ArrayList.<init>()V
PUTFIELD az.b Ljava/util/List;
ALOAD this
DUP
ASTORE 1
NEW javax/swing/JPanel
DUP
INVOKESPECIAL javax/swing/JPanel.<init>()V
PUTFIELD az.c Ljavax/swing/JPanel;
ALOAD 1
NEW javax/swing/JPanel
DUP
INVOKESPECIAL javax/swing/JPanel.<init>()V
PUTFIELD az.e Ljavax/swing/JPanel;
ALOAD 1
NEW javax/swing/JButton
DUP
INVOKESPECIAL javax/swing/JButton.<init>()V
PUTFIELD az.c Ljavax/swing/JButton;
ALOAD 1
NEW javax/swing/JButton
DUP
INVOKESPECIAL javax/swing/JButton.<init>()V
PUTFIELD az.a Ljavax/swing/JButton;
ALOAD 1
NEW javax/swing/JButton
DUP
INVOKESPECIAL javax/swing/JButton.<init>()V
PUTFIELD az.b Ljavax/swing/JButton;
ALOAD 1
NEW javax/swing/JLabel
DUP
INVOKESPECIAL javax/swing/JLabel.<init>()V
PUTFIELD az.b Ljavax/swing/JLabel;
ALOAD 1
NEW javax/swing/JPanel
DUP
INVOKESPECIAL javax/swing/JPanel.<init>()V
PUTFIELD az.b Ljavax/swing/JPanel;
ALOAD 1
NEW javax/swing/JPanel
DUP
INVOKESPECIAL javax/swing/JPanel.<init>()V
PUTFIELD az.a Ljavax/swing/JPanel;
ALOAD 1
NEW javax/swing/JComboBox
DUP
INVOKESPECIAL javax/swing/JComboBox.<init>()V
PUTFIELD az.a Ljavax/swing/JComboBox;
ALOAD 1
NEW cX
DUP
INVOKESPECIAL cX.<init>()V
PUTFIELD az.a LcX;
ALOAD 1
NEW cT
DUP
INVOKESPECIAL cT.<init>()V
PUTFIELD az.d LcT;
ALOAD 1
NEW cT
DUP
INVOKESPECIAL cT.<init>()V
PUTFIELD az.b LcT;
ALOAD 1
NEW cT
DUP
INVOKESPECIAL cT.<init>()V
PUTFIELD az.a LcT;
ALOAD 1
NEW cT
DUP
INVOKESPECIAL cT.<init>()V
PUTFIELD az.c LcT;
ALOAD 1
NEW cT
DUP
INVOKESPECIAL cT.<init>()V
PUTFIELD az.h LcT;
ALOAD 1
NEW cT
DUP
INVOKESPECIAL cT.<init>()V
PUTFIELD az.f LcT;
ALOAD 1
NEW cT
DUP
INVOKESPECIAL cT.<init>()V
PUTFIELD az.e LcT;
ALOAD 1
NEW cT
DUP
INVOKESPECIAL cT.<init>()V
PUTFIELD az.i LcT;
ALOAD 1
NEW cT
DUP
INVOKESPECIAL cT.<init>()V
PUTFIELD az.g LcT;
ALOAD 1
NEW javax/swing/JPanel
DUP
INVOKESPECIAL javax/swing/JPanel.<init>()V
PUTFIELD az.g Ljavax/swing/JPanel;
ALOAD 1
NEW javax/swing/JTextField
DUP
INVOKESPECIAL javax/swing/JTextField.<init>()V
PUTFIELD az.a Ljavax/swing/JTextField;
ALOAD 1
NEW javax/swing/JFormattedTextField
DUP
INVOKESPECIAL javax/swing/JFormattedTextField.<init>()V
PUTFIELD az.a Ljavax/swing/JFormattedTextField;
ALOAD 1
NEW dg
DUP
INVOKESPECIAL dg.<init>()V
PUTFIELD az.a Ldg;
ALOAD 1
NEW dg
DUP
INVOKESPECIAL dg.<init>()V
PUTFIELD az.b Ldg;
ALOAD 1
NEW javax/swing/JPanel
DUP
INVOKESPECIAL javax/swing/JPanel.<init>()V
PUTFIELD az.f Ljavax/swing/JPanel;
ALOAD 1
NEW javax/swing/JComboBox
DUP
INVOKESPECIAL javax/swing/JComboBox.<init>()V
PUTFIELD az.b Ljavax/swing/JComboBox;
ALOAD 1
NEW javax/swing/JPanel
DUP
INVOKESPECIAL javax/swing/JPanel.<init>()V
PUTFIELD az.d Ljavax/swing/JPanel;
ALOAD 1
NEW javax/swing/JLabel
DUP
INVOKESPECIAL javax/swing/JLabel.<init>()V
PUTFIELD az.a Ljavax/swing/JLabel;
ALOAD 1
NEW javax/swing/JSeparator
DUP
INVOKESPECIAL javax/swing/JSeparator.<init>()V
PUTFIELD az.a Ljavax/swing/JSeparator;
ALOAD 1
NEW javax/swing/JProgressBar
DUP
INVOKESPECIAL javax/swing/JProgressBar.<init>()V
PUTFIELD az.a Ljavax/swing/JProgressBar;
ALOAD 1
NEW javax/swing/JLabel
DUP
INVOKESPECIAL javax/swing/JLabel.<init>()V
PUTFIELD az.c Ljavax/swing/JLabel;
ALOAD 1
ICONST_0
INVOKEVIRTUAL az.setDefaultCloseOperation(I)V
ALOAD 1
LDC "MobyDroid"
INVOKEVIRTUAL az.setTitle(Ljava/lang/String;)V
ALOAD 1
NEW java/awt/Dimension
DUP
SIPUSH 1024
SIPUSH 496
INVOKESPECIAL java/awt/Dimension.<init>(II)V
INVOKEVIRTUAL az.setMinimumSize(Ljava/awt/Dimension;)V
ALOAD 1
LDC "MainFrame"
INVOKEVIRTUAL az.setName(Ljava/lang/String;)V
ALOAD 1
ICONST_1
INVOKEVIRTUAL az.setUndecorated(Z)V
ALOAD 1
NEW java/awt/Dimension
DUP
ICONST_0
ICONST_0
INVOKESPECIAL java/awt/Dimension.<init>(II)V
INVOKEVIRTUAL az.setSize(Ljava/awt/Dimension;)V
ALOAD 1
NEW aL
DUP
ALOAD 1
INVOKESPECIAL aL.<init>(Laz;)V
INVOKEVIRTUAL az.addWindowListener(Ljava/awt/event/WindowListener;)V
ALOAD 1
GETFIELD az.c Ljavax/swing/JPanel;
NEW java/awt/Color
DUP
SIPUSH 250
SIPUSH 250
SIPUSH 250
INVOKESPECIAL java/awt/Color.<init>(III)V
INVOKEVIRTUAL javax/swing/JPanel.setBackground(Ljava/awt/Color;)V
ALOAD 1
GETFIELD az.e Ljavax/swing/JPanel;
NEW java/awt/Color
DUP
BIPUSH 25
BIPUSH 118
SIPUSH 210
INVOKESPECIAL java/awt/Color.<init>(III)V
INVOKEVIRTUAL javax/swing/JPanel.setBackground(Ljava/awt/Color;)V
ALOAD 1
GETFIELD az.e Ljavax/swing/JPanel;
NEW java/awt/Color
DUP
BIPUSH 25
BIPUSH 118
SIPUSH 210
INVOKESPECIAL java/awt/Color.<init>(III)V
INVOKESTATIC javax/swing/BorderFactory.createLineBorder(Ljava/awt/Color;)Ljavax/swing/border/Border;
INVOKEVIRTUAL javax/swing/JPanel.setBorder(Ljavax/swing/border/Border;)V
ALOAD 1
GETFIELD az.c Ljavax/swing/JButton;
NEW java/awt/Color
DUP
BIPUSH 25
BIPUSH 118
SIPUSH 210
INVOKESPECIAL java/awt/Color.<init>(III)V
INVOKEVIRTUAL javax/swing/JButton.setBackground(Ljava/awt/Color;)V
ALOAD 1
GETFIELD az.c Ljavax/swing/JButton;
GETSTATIC aa.a Ljava/awt/Font;
LDC 20.0F
INVOKEVIRTUAL java/awt/Font.deriveFont(F)Ljava/awt/Font;
INVOKEVIRTUAL javax/swing/JButton.setFont(Ljava/awt/Font;)V
ALOAD 1
GETFIELD az.c Ljavax/swing/JButton;
NEW java/awt/Color
DUP
SIPUSH 255
SIPUSH 255
SIPUSH 255
INVOKESPECIAL java/awt/Color.<init>(III)V
INVOKEVIRTUAL javax/swing/JButton.setForeground(Ljava/awt/Color;)V
ALOAD 1
GETFIELD az.c Ljavax/swing/JButton;
LDC ""
INVOKEVIRTUAL javax/swing/JButton.setText(Ljava/lang/String;)V
ALOAD 1
GETFIELD az.c Ljavax/swing/JButton;
LDC "Minimize"
INVOKEVIRTUAL javax/swing/JButton.setToolTipText(Ljava/lang/String;)V
ALOAD 1
GETFIELD az.c Ljavax/swing/JButton;
NEW java/awt/Color
DUP
ICONST_0
ICONST_0
ICONST_0
INVOKESPECIAL java/awt/Color.<init>(III)V
INVOKESTATIC javax/swing/BorderFactory.createLineBorder(Ljava/awt/Color;)Ljavax/swing/border/Border;
INVOKEVIRTUAL javax/swing/JButton.setBorder(Ljavax/swing/border/Border;)V
ALOAD 1
GETFIELD az.c Ljavax/swing/JButton;
ICONST_0
INVOKEVIRTUAL javax/swing/JButton.setBorderPainted(Z)V
ALOAD 1
GETFIELD az.c Ljavax/swing/JButton;
NEW aN
DUP
ALOAD 1
INVOKESPECIAL aN.<init>(Laz;)V
INVOKEVIRTUAL javax/swing/JButton.addActionListener(Ljava/awt/event/ActionListener;)V
ALOAD 1
GETFIELD az.a Ljavax/swing/JButton;
NEW java/awt/Color
DUP
BIPUSH 25
BIPUSH 118
SIPUSH 210
INVOKESPECIAL java/awt/Color.<init>(III)V
INVOKEVIRTUAL javax/swing/JButton.setBackground(Ljava/awt/Color;)V
ALOAD 1
GETFIELD az.a Ljavax/swing/JButton;
GETSTATIC aa.a Ljava/awt/Font;
LDC 20.0F
INVOKEVIRTUAL java/awt/Font.deriveFont(F)Ljava/awt/Font;
INVOKEVIRTUAL javax/swing/JButton.setFont(Ljava/awt/Font;)V
ALOAD 1
GETFIELD az.a Ljavax/swing/JButton;
NEW java/awt/Color
DUP
SIPUSH 255
SIPUSH 255
SIPUSH 255
INVOKESPECIAL java/awt/Color.<init>(III)V
INVOKEVIRTUAL javax/swing/JButton.setForeground(Ljava/awt/Color;)V
ALOAD 1
GETFIELD az.a Ljavax/swing/JButton;
LDC ""
INVOKEVIRTUAL javax/swing/JButton.setText(Ljava/lang/String;)V
ALOAD 1
GETFIELD az.a Ljavax/swing/JButton;
LDC "Exit"
INVOKEVIRTUAL javax/swing/JButton.setToolTipText(Ljava/lang/String;)V
ALOAD 1
GETFIELD az.a Ljavax/swing/JButton;
NEW java/awt/Color
DUP
ICONST_0
ICONST_0
ICONST_0
INVOKESPECIAL java/awt/Color.<init>(III)V
INVOKESTATIC javax/swing/BorderFactory.createLineBorder(Ljava/awt/Color;)Ljavax/swing/border/Border;
INVOKEVIRTUAL javax/swing/JButton.setBorder(Ljavax/swing/border/Border;)V
ALOAD 1
GETFIELD az.a Ljavax/swing/JButton;
ICONST_0
INVOKEVIRTUAL javax/swing/JButton.setBorderPainted(Z)V
ALOAD 1
GETFIELD az.a Ljavax/swing/JButton;
NEW aO
DUP
ALOAD 1
INVOKESPECIAL aO.<init>(Laz;)V
INVOKEVIRTUAL javax/swing/JButton.addActionListener(Ljava/awt/event/ActionListener;)V
ALOAD 1
GETFIELD az.b Ljavax/swing/JButton;
NEW java/awt/Color
DUP
BIPUSH 25
BIPUSH 118
SIPUSH 210
INVOKESPECIAL java/awt/Color.<init>(III)V
INVOKEVIRTUAL javax/swing/JButton.setBackground(Ljava/awt/Color;)V
ALOAD 1
GETFIELD az.b Ljavax/swing/JButton;
GETSTATIC aa.a Ljava/awt/Font;
LDC 20.0F
INVOKEVIRTUAL java/awt/Font.deriveFont(F)Ljava/awt/Font;
INVOKEVIRTUAL javax/swing/JButton.setFont(Ljava/awt/Font;)V
ALOAD 1
GETFIELD az.b Ljavax/swing/JButton;
NEW java/awt/Color
DUP
SIPUSH 255
SIPUSH 255
SIPUSH 255
INVOKESPECIAL java/awt/Color.<init>(III)V
INVOKEVIRTUAL javax/swing/JButton.setForeground(Ljava/awt/Color;)V
ALOAD 1
GETFIELD az.b Ljavax/swing/JButton;
LDC ""
INVOKEVIRTUAL javax/swing/JButton.setText(Ljava/lang/String;)V
ALOAD 1
GETFIELD az.b Ljavax/swing/JButton;
LDC "Maximize"
INVOKEVIRTUAL javax/swing/JButton.setToolTipText(Ljava/lang/String;)V
ALOAD 1
GETFIELD az.b Ljavax/swing/JButton;
NEW java/awt/Color
DUP
ICONST_0
ICONST_0
ICONST_0
INVOKESPECIAL java/awt/Color.<init>(III)V
INVOKESTATIC javax/swing/BorderFactory.createLineBorder(Ljava/awt/Color;)Ljavax/swing/border/Border;
INVOKEVIRTUAL javax/swing/JButton.setBorder(Ljavax/swing/border/Border;)V
ALOAD 1
GETFIELD az.b Ljavax/swing/JButton;
ICONST_0
INVOKEVIRTUAL javax/swing/JButton.setBorderPainted(Z)V
ALOAD 1
GETFIELD az.b Ljavax/swing/JButton;
NEW aP
DUP
ALOAD 1
INVOKESPECIAL aP.<init>(Laz;)V
INVOKEVIRTUAL javax/swing/JButton.addActionListener(Ljava/awt/event/ActionListener;)V
ALOAD 1
GETFIELD az.b Ljavax/swing/JLabel;
NEW java/awt/Font
DUP
LDC "Dialog"
ICONST_1
BIPUSH 18
INVOKESPECIAL java/awt/Font.<init>(Ljava/lang/String;II)V
INVOKEVIRTUAL javax/swing/JLabel.setFont(Ljava/awt/Font;)V
ALOAD 1
GETFIELD az.b Ljavax/swing/JLabel;
NEW java/awt/Color
DUP
SIPUSH 255
SIPUSH 255
SIPUSH 255
INVOKESPECIAL java/awt/Color.<init>(III)V
INVOKEVIRTUAL javax/swing/JLabel.setForeground(Ljava/awt/Color;)V
ALOAD 1
GETFIELD az.b Ljavax/swing/JLabel;
LDC "MobyDroid"
INVOKEVIRTUAL javax/swing/JLabel.setText(Ljava/lang/String;)V
NEW javax/swing/GroupLayout
DUP
ALOAD 1
GETFIELD az.e Ljavax/swing/JPanel;
INVOKESPECIAL javax/swing/GroupLayout.<init>(Ljava/awt/Container;)V
ASTORE 2
ALOAD 1
GETFIELD az.e Ljavax/swing/JPanel;
ALOAD 2
INVOKEVIRTUAL javax/swing/JPanel.setLayout(Ljava/awt/LayoutManager;)V
ALOAD 2
DUP
GETSTATIC javax/swing/GroupLayout$Alignment.LEADING Ljavax/swing/GroupLayout$Alignment;
INVOKEVIRTUAL javax/swing/GroupLayout.createParallelGroup(Ljavax/swing/GroupLayout$Alignment;)Ljavax/swing/GroupLayout$ParallelGroup;
GETSTATIC javax/swing/GroupLayout$Alignment.TRAILING Ljavax/swing/GroupLayout$Alignment;
ALOAD 2
INVOKEVIRTUAL javax/swing/GroupLayout.createSequentialGroup()Ljavax/swing/GroupLayout$SequentialGroup;
INVOKEVIRTUAL javax/swing/GroupLayout$SequentialGroup.addContainerGap()Ljavax/swing/GroupLayout$SequentialGroup;
ALOAD 1
GETFIELD az.b Ljavax/swing/JLabel;
ICONST_M1
ICONST_M1
SIPUSH 32767
INVOKEVIRTUAL javax/swing/GroupLayout$SequentialGroup.addComponent(Ljava/awt/Component;III)Ljavax/swing/GroupLayout$SequentialGroup;
GETSTATIC javax/swing/LayoutStyle$ComponentPlacement.RELATED Ljavax/swing/LayoutStyle$ComponentPlacement;
INVOKEVIRTUAL javax/swing/GroupLayout$SequentialGroup.addPreferredGap(Ljavax/swing/LayoutStyle$ComponentPlacement;)Ljavax/swing/GroupLayout$SequentialGroup;
ALOAD 1
GETFIELD az.c Ljavax/swing/JButton;
BIPUSH -2
BIPUSH 32
BIPUSH -2
INVOKEVIRTUAL javax/swing/GroupLayout$SequentialGroup.addComponent(Ljava/awt/Component;III)Ljavax/swing/GroupLayout$SequentialGroup;
GETSTATIC javax/swing/LayoutStyle$ComponentPlacement.RELATED Ljavax/swing/LayoutStyle$ComponentPlacement;
INVOKEVIRTUAL javax/swing/GroupLayout$SequentialGroup.addPreferredGap(Ljavax/swing/LayoutStyle$ComponentPlacement;)Ljavax/swing/GroupLayout$SequentialGroup;
ALOAD 1
GETFIELD az.b Ljavax/swing/JButton;
BIPUSH -2
BIPUSH 32
BIPUSH -2
INVOKEVIRTUAL javax/swing/GroupLayout$SequentialGroup.addComponent(Ljava/awt/Component;III)Ljavax/swing/GroupLayout$SequentialGroup;
GETSTATIC javax/swing/LayoutStyle$ComponentPlacement.RELATED Ljavax/swing/LayoutStyle$ComponentPlacement;
INVOKEVIRTUAL javax/swing/GroupLayout$SequentialGroup.addPreferredGap(Ljavax/swing/LayoutStyle$ComponentPlacement;)Ljavax/swing/GroupLayout$SequentialGroup;
ALOAD 1
GETFIELD az.a Ljavax/swing/JButton;
BIPUSH -2
BIPUSH 32
BIPUSH -2
INVOKEVIRTUAL javax/swing/GroupLayout$SequentialGroup.addComponent(Ljava/awt/Component;III)Ljavax/swing/GroupLayout$SequentialGroup;
INVOKEVIRTUAL javax/swing/GroupLayout$SequentialGroup.addContainerGap()Ljavax/swing/GroupLayout$SequentialGroup;
INVOKEVIRTUAL javax/swing/GroupLayout$ParallelGroup.addGroup(Ljavax/swing/GroupLayout$Alignment;Ljavax/swing/GroupLayout$Group;)Ljavax/swing/GroupLayout$ParallelGroup;
INVOKEVIRTUAL javax/swing/GroupLayout.setHorizontalGroup(Ljavax/swing/GroupLayout$Group;)V
ALOAD 2
DUP
GETSTATIC javax/swing/GroupLayout$Alignment.LEADING Ljavax/swing/GroupLayout$Alignment;
INVOKEVIRTUAL javax/swing/GroupLayout.createParallelGroup(Ljavax/swing/GroupLayout$Alignment;)Ljavax/swing/GroupLayout$ParallelGroup;
ALOAD 2
INVOKEVIRTUAL javax/swing/GroupLayout.createSequentialGroup()Ljavax/swing/GroupLayout$SequentialGroup;
BIPUSH 6
BIPUSH 6
BIPUSH 6
INVOKEVIRTUAL javax/swing/GroupLayout$SequentialGroup.addGap(III)Ljavax/swing/GroupLayout$SequentialGroup;
ALOAD 2
GETSTATIC javax/swing/GroupLayout$Alignment.TRAILING Ljavax/swing/GroupLayout$Alignment;
INVOKEVIRTUAL javax/swing/GroupLayout.createParallelGroup(Ljavax/swing/GroupLayout$Alignment;)Ljavax/swing/GroupLayout$ParallelGroup;
ALOAD 1
GETFIELD az.b Ljavax/swing/JLabel;
BIPUSH -2
BIPUSH 32
BIPUSH -2
INVOKEVIRTUAL javax/swing/GroupLayout$ParallelGroup.addComponent(Ljava/awt/Component;III)Ljavax/swing/GroupLayout$ParallelGroup;
GETSTATIC javax/swing/GroupLayout$Alignment.LEADING Ljavax/swing/GroupLayout$Alignment;
ALOAD 2
GETSTATIC javax/swing/GroupLayout$Alignment.BASELINE Ljavax/swing/GroupLayout$Alignment;
INVOKEVIRTUAL javax/swing/GroupLayout.createParallelGroup(Ljavax/swing/GroupLayout$Alignment;)Ljavax/swing/GroupLayout$ParallelGroup;
ALOAD 1
GETFIELD az.b Ljavax/swing/JButton;
BIPUSH -2
BIPUSH 32
BIPUSH -2
INVOKEVIRTUAL javax/swing/GroupLayout$ParallelGroup.addComponent(Ljava/awt/Component;III)Ljavax/swing/GroupLayout$ParallelGroup;
ALOAD 1
GETFIELD az.a Ljavax/swing/JButton;
BIPUSH -2
BIPUSH 32
BIPUSH -2
INVOKEVIRTUAL javax/swing/GroupLayout$ParallelGroup.addComponent(Ljava/awt/Component;III)Ljavax/swing/GroupLayout$ParallelGroup;
ALOAD 1
GETFIELD az.c Ljavax/swing/JButton;
BIPUSH -2
BIPUSH 32
BIPUSH -2
INVOKEVIRTUAL javax/swing/GroupLayout$ParallelGroup.addComponent(Ljava/awt/Component;III)Ljavax/swing/GroupLayout$ParallelGroup;
INVOKEVIRTUAL javax/swing/GroupLayout$ParallelGroup.addGroup(Ljavax/swing/GroupLayout$Alignment;Ljavax/swing/GroupLayout$Group;)Ljavax/swing/GroupLayout$ParallelGroup;
INVOKEVIRTUAL javax/swing/GroupLayout$SequentialGroup.addGroup(Ljavax/swing/GroupLayout$Group;)Ljavax/swing/GroupLayout$SequentialGroup;
BIPUSH 6
BIPUSH 6
BIPUSH 6
INVOKEVIRTUAL javax/swing/GroupLayout$SequentialGroup.addGap(III)Ljavax/swing/GroupLayout$SequentialGroup;
INVOKEVIRTUAL javax/swing/GroupLayout$ParallelGroup.addGroup(Ljavax/swing/GroupLayout$Group;)Ljavax/swing/GroupLayout$ParallelGroup;
INVOKEVIRTUAL javax/swing/GroupLayout.setVerticalGroup(Ljavax/swing/GroupLayout$Group;)V
ALOAD 1
GETFIELD az.b Ljavax/swing/JPanel;
NEW java/awt/Color
DUP
SIPUSH 250
SIPUSH 250
SIPUSH 250
INVOKESPECIAL java/awt/Color.<init>(III)V
INVOKEVIRTUAL javax/swing/JPanel.setBackground(Ljava/awt/Color;)V
ALOAD 1
GETFIELD az.b Ljavax/swing/JPanel;
NEW java/awt/Color
DUP
SIPUSH 217
SIPUSH 217
SIPUSH 217
INVOKESPECIAL java/awt/Color.<init>(III)V
INVOKESTATIC javax/swing/BorderFactory.createLineBorder(Ljava/awt/Color;)Ljavax/swing/border/Border;
INVOKEVIRTUAL javax/swing/JPanel.setBorder(Ljavax/swing/border/Border;)V
NEW javax/swing/GroupLayout
DUP
ALOAD 1
GETFIELD az.b Ljavax/swing/JPanel;
INVOKESPECIAL javax/swing/GroupLayout.<init>(Ljava/awt/Container;)V
ASTORE 2
ALOAD 1
GETFIELD az.b Ljavax/swing/JPanel;
ALOAD 2
INVOKEVIRTUAL javax/swing/JPanel.setLayout(Ljava/awt/LayoutManager;)V
ALOAD 2
DUP
GETSTATIC javax/swing/GroupLayout$Alignment.LEADING Ljavax/swing/GroupLayout$Alignment;
INVOKEVIRTUAL javax/swing/GroupLayout.createParallelGroup(Ljavax/swing/GroupLayout$Alignment;)Ljavax/swing/GroupLayout$ParallelGroup;
ICONST_0
SIPUSH 741
SIPUSH 32767
INVOKEVIRTUAL javax/swing/GroupLayout$ParallelGroup.addGap(III)Ljavax/swing/GroupLayout$ParallelGroup;
INVOKEVIRTUAL javax/swing/GroupLayout.setHorizontalGroup(Ljavax/swing/GroupLayout$Group;)V
ALOAD 2
DUP
GETSTATIC javax/swing/GroupLayout$Alignment.LEADING Ljavax/swing/GroupLayout$Alignment;
INVOKEVIRTUAL javax/swing/GroupLayout.createParallelGroup(Ljavax/swing/GroupLayout$Alignment;)Ljavax/swing/GroupLayout$ParallelGroup;
ICONST_0
SIPUSH 595
SIPUSH 32767
INVOKEVIRTUAL javax/swing/GroupLayout$ParallelGroup.addGap(III)Ljavax/swing/GroupLayout$ParallelGroup;
INVOKEVIRTUAL javax/swing/GroupLayout.setVerticalGroup(Ljavax/swing/GroupLayout$Group;)V
ALOAD 1
GETFIELD az.a Ljavax/swing/JPanel;
NEW java/awt/Color
DUP
SIPUSH 250
SIPUSH 250
SIPUSH 250
INVOKESPECIAL java/awt/Color.<init>(III)V
INVOKEVIRTUAL javax/swing/JPanel.setBackground(Ljava/awt/Color;)V
ALOAD 1
GETFIELD az.a Ljavax/swing/JPanel;
NEW java/awt/Color
DUP
SIPUSH 217
SIPUSH 217
SIPUSH 217
INVOKESPECIAL java/awt/Color.<init>(III)V
INVOKESTATIC javax/swing/BorderFactory.createLineBorder(Ljava/awt/Color;)Ljavax/swing/border/Border;
INVOKEVIRTUAL javax/swing/JPanel.setBorder(Ljavax/swing/border/Border;)V
ALOAD 1
GETFIELD az.a Ljavax/swing/JComboBox;
NEW java/awt/Color
DUP
SIPUSH 250
SIPUSH 250
SIPUSH 250
INVOKESPECIAL java/awt/Color.<init>(III)V
INVOKEVIRTUAL javax/swing/JComboBox.setBackground(Ljava/awt/Color;)V
ALOAD 1
GETFIELD az.a Ljavax/swing/JComboBox;
NEW java/awt/Font
DUP
LDC "Dialog"
ICONST_0
BIPUSH 12
INVOKESPECIAL java/awt/Font.<init>(Ljava/lang/String;II)V
INVOKEVIRTUAL javax/swing/JComboBox.setFont(Ljava/awt/Font;)V
ALOAD 1
GETFIELD az.a Ljavax/swing/JComboBox;
NEW java/awt/Color
DUP
BIPUSH 97
BIPUSH 97
BIPUSH 97
INVOKESPECIAL java/awt/Color.<init>(III)V
INVOKEVIRTUAL javax/swing/JComboBox.setForeground(Ljava/awt/Color;)V
ALOAD 1
GETFIELD az.a Ljavax/swing/JComboBox;
NEW java/awt/Color
DUP
SIPUSH 250
SIPUSH 250
SIPUSH 250
INVOKESPECIAL java/awt/Color.<init>(III)V
INVOKESTATIC javax/swing/BorderFactory.createLineBorder(Ljava/awt/Color;)Ljavax/swing/border/Border;
INVOKEVIRTUAL javax/swing/JComboBox.setBorder(Ljavax/swing/border/Border;)V
ALOAD 1
GETFIELD az.a Ljavax/swing/JComboBox;
NEW java/awt/Dimension
DUP
BIPUSH 36
BIPUSH 28
INVOKESPECIAL java/awt/Dimension.<init>(II)V
INVOKEVIRTUAL javax/swing/JComboBox.setPreferredSize(Ljava/awt/Dimension;)V
ALOAD 1
GETFIELD az.a Ljavax/swing/JComboBox;
NEW aV
DUP
ALOAD 1
INVOKESPECIAL aV.<init>(Laz;)V
INVOKEVIRTUAL javax/swing/JComboBox.setRenderer(Ljavax/swing/ListCellRenderer;)V
ALOAD 1
GETFIELD az.a Ljavax/swing/JComboBox;
NEW aQ
DUP
ALOAD 1
INVOKESPECIAL aQ.<init>(Laz;)V
INVOKEVIRTUAL javax/swing/JComboBox.addItemListener(Ljava/awt/event/ItemListener;)V
ALOAD 1
GETFIELD az.a LcX;
LDC "SuROOT"
INVOKEVIRTUAL cX.setToolTipText(Ljava/lang/String;)V
ALOAD 1
GETFIELD az.a LcX;
NEW aR
DUP
ALOAD 1
INVOKESPECIAL aR.<init>(Laz;)V
INVOKEVIRTUAL cX.a(LH;)V
ALOAD 1
GETFIELD az.a LcX;
FCONST_0
INVOKEVIRTUAL cX.setAlignmentX(F)V
ALOAD 1
GETFIELD az.a LcX;
FCONST_0
INVOKEVIRTUAL cX.setAlignmentY(F)V
ALOAD 1
GETFIELD az.a LcX;
ICONST_1
INVOKEVIRTUAL cX.setFocusable(Z)V
ALOAD 1
GETFIELD az.a LcX;
LDC 57566
INVOKEVIRTUAL cX.a(C)V
ALOAD 1
GETFIELD az.d LcT;
NEW aS
DUP
ALOAD 1
INVOKESPECIAL aS.<init>(Laz;)V
INVOKEVIRTUAL cT.a(LH;)V
ALOAD 1
GETFIELD az.d LcT;
ICONST_1
INVOKEVIRTUAL cT.setFocusable(Z)V
ALOAD 1
GETFIELD az.d LcT;
LDC 59530
INVOKEVIRTUAL cT.a(C)V
ALOAD 1
GETFIELD az.d LcT;
LDC "Home"
INVOKEVIRTUAL cT.a(Ljava/lang/String;)V
ALOAD 1
GETFIELD az.b LcT;
NEW aT
DUP
ALOAD 1
INVOKESPECIAL aT.<init>(Laz;)V
INVOKEVIRTUAL cT.a(LH;)V
ALOAD 1
GETFIELD az.b LcT;
ICONST_1
INVOKEVIRTUAL cT.setFocusable(Z)V
ALOAD 1
GETFIELD az.b LcT;
LDC 58819
INVOKEVIRTUAL cT.a(C)V
ALOAD 1
GETFIELD az.b LcT;
LDC "App Manager"
INVOKEVIRTUAL cT.a(Ljava/lang/String;)V
ALOAD 1
GETFIELD az.a LcT;
NEW aB
DUP
ALOAD 1
INVOKESPECIAL aB.<init>(Laz;)V
INVOKEVIRTUAL cT.a(LH;)V
ALOAD 1
GETFIELD az.a LcT;
ICONST_1
INVOKEVIRTUAL cT.setFocusable(Z)V
ALOAD 1
GETFIELD az.a LcT;
LDC 57673
INVOKEVIRTUAL cT.a(C)V
ALOAD 1
GETFIELD az.a LcT;
LDC "App Installer"
INVOKEVIRTUAL cT.a(Ljava/lang/String;)V
ALOAD 1
GETFIELD az.c LcT;
NEW aC
DUP
ALOAD 1
INVOKESPECIAL aC.<init>(Laz;)V
INVOKEVIRTUAL cT.a(LH;)V
ALOAD 1
GETFIELD az.c LcT;
ICONST_1
INVOKEVIRTUAL cT.setFocusable(Z)V
ALOAD 1
GETFIELD az.c LcT;
LDC 58056
INVOKEVIRTUAL cT.a(C)V
ALOAD 1
GETFIELD az.c LcT;
LDC "File Manager"
INVOKEVIRTUAL cT.a(Ljava/lang/String;)V
ALOAD 1
GETFIELD az.h LcT;
NEW aD
DUP
ALOAD 1
INVOKESPECIAL aD.<init>(Laz;)V
INVOKEVIRTUAL cT.a(LH;)V
ALOAD 1
GETFIELD az.h LcT;
ICONST_1
INVOKEVIRTUAL cT.setFocusable(Z)V
ALOAD 1
GETFIELD az.h LcT;
LDC 58146
INVOKEVIRTUAL cT.a(C)V
ALOAD 1
GETFIELD az.h LcT;
LDC "Tasks"
INVOKEVIRTUAL cT.a(Ljava/lang/String;)V
ALOAD 1
GETFIELD az.f LcT;
NEW aE
DUP
ALOAD 1
INVOKESPECIAL aE.<init>(Laz;)V
INVOKEVIRTUAL cT.a(LH;)V
ALOAD 1
GETFIELD az.f LcT;
ICONST_1
INVOKEVIRTUAL cT.setFocusable(Z)V
ALOAD 1
GETFIELD az.f LcT;
LDC 58386
INVOKEVIRTUAL cT.a(C)V
ALOAD 1
GETFIELD az.f LcT;
LDC "Screen Capture"
INVOKEVIRTUAL cT.a(Ljava/lang/String;)V
ALOAD 1
GETFIELD az.e LcT;
NEW aF
DUP
ALOAD 1
INVOKESPECIAL aF.<init>(Laz;)V
INVOKEVIRTUAL cT.a(LH;)V
ALOAD 1
GETFIELD az.e LcT;
ICONST_1
INVOKEVIRTUAL cT.setFocusable(Z)V
ALOAD 1
GETFIELD az.e LcT;
LDC 59557
INVOKEVIRTUAL cT.a(C)V
ALOAD 1
GETFIELD az.e LcT;
LDC "Phone Info"
INVOKEVIRTUAL cT.a(Ljava/lang/String;)V
ALOAD 1
GETFIELD az.i LcT;
NEW aG
DUP
ALOAD 1
INVOKESPECIAL aG.<init>(Laz;)V
INVOKEVIRTUAL cT.a(LH;)V
ALOAD 1
GETFIELD az.i LcT;
ICONST_1
INVOKEVIRTUAL cT.setFocusable(Z)V
ALOAD 1
GETFIELD az.i LcT;
LDC 57452
INVOKEVIRTUAL cT.a(C)V
ALOAD 1
GETFIELD az.i LcT;
LDC "Terminal"
INVOKEVIRTUAL cT.a(Ljava/lang/String;)V
ALOAD 1
GETFIELD az.g LcT;
NEW aH
DUP
ALOAD 1
INVOKESPECIAL aH.<init>(Laz;)V
INVOKEVIRTUAL cT.a(LH;)V
ALOAD 1
GETFIELD az.g LcT;
ICONST_1
INVOKEVIRTUAL cT.setFocusable(Z)V
ALOAD 1
GETFIELD az.g LcT;
LDC 59576
INVOKEVIRTUAL cT.a(C)V
ALOAD 1
GETFIELD az.g LcT;
LDC "Settings"
INVOKEVIRTUAL cT.a(Ljava/lang/String;)V
ALOAD 1
GETFIELD az.g Ljavax/swing/JPanel;
NEW java/awt/Color
DUP
SIPUSH 250
SIPUSH 250
SIPUSH 250
INVOKESPECIAL java/awt/Color.<init>(III)V
INVOKEVIRTUAL javax/swing/JPanel.setBackground(Ljava/awt/Color;)V
ALOAD 1
GETFIELD az.g Ljavax/swing/JPanel;
LDC "Wireless:"
INVOKESTATIC javax/swing/BorderFactory.createTitledBorder(Ljava/lang/String;)Ljavax/swing/border/TitledBorder;
INVOKEVIRTUAL javax/swing/JPanel.setBorder(Ljavax/swing/border/Border;)V
ALOAD 1
GETFIELD az.a Ljavax/swing/JTextField;
LDC "192.168.1.1"
INVOKEVIRTUAL javax/swing/JTextField.setText(Ljava/lang/String;)V
ALOAD 1
GETFIELD az.a Ljavax/swing/JTextField;
NEW java/awt/Dimension
DUP
BIPUSH 64
LDC 2147483647
INVOKESPECIAL java/awt/Dimension.<init>(II)V
INVOKEVIRTUAL javax/swing/JTextField.setMaximumSize(Ljava/awt/Dimension;)V
ALOAD 1
GETFIELD az.a Ljavax/swing/JTextField;
NEW java/awt/Dimension
DUP
ICONST_4
BIPUSH 24
INVOKESPECIAL java/awt/Dimension.<init>(II)V
INVOKEVIRTUAL javax/swing/JTextField.setPreferredSize(Ljava/awt/Dimension;)V
ALOAD 1
GETFIELD az.a Ljavax/swing/JFormattedTextField;
NEW javax/swing/text/DefaultFormatterFactory
DUP
NEW javax/swing/text/NumberFormatter
DUP
NEW java/text/DecimalFormat
DUP
LDC "#0"
INVOKESPECIAL java/text/DecimalFormat.<init>(Ljava/lang/String;)V
INVOKESPECIAL javax/swing/text/NumberFormatter.<init>(Ljava/text/NumberFormat;)V
INVOKESPECIAL javax/swing/text/DefaultFormatterFactory.<init>(Ljavax/swing/JFormattedTextField$AbstractFormatter;)V
INVOKEVIRTUAL javax/swing/JFormattedTextField.setFormatterFactory(Ljavax/swing/JFormattedTextField$AbstractFormatterFactory;)V
ALOAD 1
GETFIELD az.a Ljavax/swing/JFormattedTextField;
LDC "5555"
INVOKEVIRTUAL javax/swing/JFormattedTextField.setText(Ljava/lang/String;)V
ALOAD 1
GETFIELD az.a Ljavax/swing/JFormattedTextField;
NEW java/awt/Dimension
DUP
BIPUSH 64
LDC 2147483647
INVOKESPECIAL java/awt/Dimension.<init>(II)V
INVOKEVIRTUAL javax/swing/JFormattedTextField.setMaximumSize(Ljava/awt/Dimension;)V
ALOAD 1
GETFIELD az.a Ljavax/swing/JFormattedTextField;
NEW java/awt/Dimension
DUP
ICONST_4
BIPUSH 24
INVOKESPECIAL java/awt/Dimension.<init>(II)V
INVOKEVIRTUAL javax/swing/JFormattedTextField.setPreferredSize(Ljava/awt/Dimension;)V
ALOAD 1
GETFIELD az.a Ldg;
LDC ""
INVOKEVIRTUAL dg.setToolTipText(Ljava/lang/String;)V
ALOAD 1
GETFIELD az.a Ldg;
NEW aI
DUP
ALOAD 1
INVOKESPECIAL aI.<init>(Laz;)V
INVOKEVIRTUAL dg.a(LH;)V
ALOAD 1
GETFIELD az.a Ldg;
ICONST_1
INVOKEVIRTUAL dg.setFocusable(Z)V
ALOAD 1
GETFIELD az.a Ldg;
LDC 58050
INVOKEVIRTUAL dg.a(C)V
ALOAD 1
GETFIELD az.a Ldg;
LDC "Connect"
INVOKEVIRTUAL dg.a(Ljava/lang/String;)V
ALOAD 1
GETFIELD az.b Ldg;
LDC ""
INVOKEVIRTUAL dg.setToolTipText(Ljava/lang/String;)V
ALOAD 1
GETFIELD az.b Ldg;
NEW aJ
DUP
ALOAD 1
INVOKESPECIAL aJ.<init>(Laz;)V
INVOKEVIRTUAL dg.a(LH;)V
ALOAD 1
GETFIELD az.b Ldg;
ICONST_1
INVOKEVIRTUAL dg.setFocusable(Z)V
ALOAD 1
GETFIELD az.b Ldg;
LDC 58049
INVOKEVIRTUAL dg.a(C)V
ALOAD 1
GETFIELD az.b Ldg;
LDC "Disconnect"
INVOKEVIRTUAL dg.a(Ljava/lang/String;)V
NEW javax/swing/GroupLayout
DUP
ALOAD 1
GETFIELD az.g Ljavax/swing/JPanel;
INVOKESPECIAL javax/swing/GroupLayout.<init>(Ljava/awt/Container;)V
ASTORE 2
ALOAD 1
GETFIELD az.g Ljavax/swing/JPanel;
ALOAD 2
INVOKEVIRTUAL javax/swing/JPanel.setLayout(Ljava/awt/LayoutManager;)V
ALOAD 2
DUP
GETSTATIC javax/swing/GroupLayout$Alignment.LEADING Ljavax/swing/GroupLayout$Alignment;
INVOKEVIRTUAL javax/swing/GroupLayout.createParallelGroup(Ljavax/swing/GroupLayout$Alignment;)Ljavax/swing/GroupLayout$ParallelGroup;
GETSTATIC javax/swing/GroupLayout$Alignment.TRAILING Ljavax/swing/GroupLayout$Alignment;
ALOAD 2
INVOKEVIRTUAL javax/swing/GroupLayout.createSequentialGroup()Ljavax/swing/GroupLayout$SequentialGroup;
ICONST_0
ICONST_0
ICONST_0
INVOKEVIRTUAL javax/swing/GroupLayout$SequentialGroup.addGap(III)Ljavax/swing/GroupLayout$SequentialGroup;
ALOAD 2
GETSTATIC javax/swing/GroupLayout$Alignment.LEADING Ljavax/swing/GroupLayout$Alignment;
INVOKEVIRTUAL javax/swing/GroupLayout.createParallelGroup(Ljavax/swing/GroupLayout$Alignment;)Ljavax/swing/GroupLayout$ParallelGroup;
ALOAD 2
INVOKEVIRTUAL javax/swing/GroupLayout.createSequentialGroup()Ljavax/swing/GroupLayout$SequentialGroup;
ALOAD 1
GETFIELD az.a Ljavax/swing/JTextField;
ICONST_M1
ICONST_M1
SIPUSH 32767
INVOKEVIRTUAL javax/swing/GroupLayout$SequentialGroup.addComponent(Ljava/awt/Component;III)Ljavax/swing/GroupLayout$SequentialGroup;
GETSTATIC javax/swing/LayoutStyle$ComponentPlacement.RELATED Ljavax/swing/LayoutStyle$ComponentPlacement;
INVOKEVIRTUAL javax/swing/GroupLayout$SequentialGroup.addPreferredGap(Ljavax/swing/LayoutStyle$ComponentPlacement;)Ljavax/swing/GroupLayout$SequentialGroup;
ALOAD 1
GETFIELD az.a Ljavax/swing/JFormattedTextField;
BIPUSH -2
BIPUSH 50
BIPUSH -2
INVOKEVIRTUAL javax/swing/GroupLayout$SequentialGroup.addComponent(Ljava/awt/Component;III)Ljavax/swing/GroupLayout$SequentialGroup;
INVOKEVIRTUAL javax/swing/GroupLayout$ParallelGroup.addGroup(Ljavax/swing/GroupLayout$Group;)Ljavax/swing/GroupLayout$ParallelGroup;
ALOAD 2
INVOKEVIRTUAL javax/swing/GroupLayout.createSequentialGroup()Ljavax/swing/GroupLayout$SequentialGroup;
ALOAD 1
GETFIELD az.a Ldg;
BIPUSH -2
ICONST_M1
BIPUSH -2
INVOKEVIRTUAL javax/swing/GroupLayout$SequentialGroup.addComponent(Ljava/awt/Component;III)Ljavax/swing/GroupLayout$SequentialGroup;
GETSTATIC javax/swing/LayoutStyle$ComponentPlacement.RELATED Ljavax/swing/LayoutStyle$ComponentPlacement;
BIPUSH 12
SIPUSH 32767
INVOKEVIRTUAL javax/swing/GroupLayout$SequentialGroup.addPreferredGap(Ljavax/swing/LayoutStyle$ComponentPlacement;II)Ljavax/swing/GroupLayout$SequentialGroup;
ALOAD 1
GETFIELD az.b Ldg;
BIPUSH -2
ICONST_M1
BIPUSH -2
INVOKEVIRTUAL javax/swing/GroupLayout$SequentialGroup.addComponent(Ljava/awt/Component;III)Ljavax/swing/GroupLayout$SequentialGroup;
INVOKEVIRTUAL javax/swing/GroupLayout$ParallelGroup.addGroup(Ljavax/swing/GroupLayout$Group;)Ljavax/swing/GroupLayout$ParallelGroup;
INVOKEVIRTUAL javax/swing/GroupLayout$SequentialGroup.addGroup(Ljavax/swing/GroupLayout$Group;)Ljavax/swing/GroupLayout$SequentialGroup;
INVOKEVIRTUAL javax/swing/GroupLayout$ParallelGroup.addGroup(Ljavax/swing/GroupLayout$Alignment;Ljavax/swing/GroupLayout$Group;)Ljavax/swing/GroupLayout$ParallelGroup;
INVOKEVIRTUAL javax/swing/GroupLayout.setHorizontalGroup(Ljavax/swing/GroupLayout$Group;)V
ALOAD 2
DUP
GETSTATIC javax/swing/GroupLayout$Alignment.LEADING Ljavax/swing/GroupLayout$Alignment;
INVOKEVIRTUAL javax/swing/GroupLayout.createParallelGroup(Ljavax/swing/GroupLayout$Alignment;)Ljavax/swing/GroupLayout$ParallelGroup;
ALOAD 2
INVOKEVIRTUAL javax/swing/GroupLayout.createSequentialGroup()Ljavax/swing/GroupLayout$SequentialGroup;
ALOAD 2
GETSTATIC javax/swing/GroupLayout$Alignment.BASELINE Ljavax/swing/GroupLayout$Alignment;
INVOKEVIRTUAL javax/swing/GroupLayout.createParallelGroup(Ljavax/swing/GroupLayout$Alignment;)Ljavax/swing/GroupLayout$ParallelGroup;
ALOAD 1
GETFIELD az.a Ljavax/swing/JTextField;
BIPUSH -2
ICONST_M1
BIPUSH -2
INVOKEVIRTUAL javax/swing/GroupLayout$ParallelGroup.addComponent(Ljava/awt/Component;III)Ljavax/swing/GroupLayout$ParallelGroup;
ALOAD 1
GETFIELD az.a Ljavax/swing/JFormattedTextField;
BIPUSH -2
ICONST_M1
BIPUSH -2
INVOKEVIRTUAL javax/swing/GroupLayout$ParallelGroup.addComponent(Ljava/awt/Component;III)Ljavax/swing/GroupLayout$ParallelGroup;
INVOKEVIRTUAL javax/swing/GroupLayout$SequentialGroup.addGroup(Ljavax/swing/GroupLayout$Group;)Ljavax/swing/GroupLayout$SequentialGroup;
GETSTATIC javax/swing/LayoutStyle$ComponentPlacement.RELATED Ljavax/swing/LayoutStyle$ComponentPlacement;
INVOKEVIRTUAL javax/swing/GroupLayout$SequentialGroup.addPreferredGap(Ljavax/swing/LayoutStyle$ComponentPlacement;)Ljavax/swing/GroupLayout$SequentialGroup;
ALOAD 2
GETSTATIC javax/swing/GroupLayout$Alignment.LEADING Ljavax/swing/GroupLayout$Alignment;
INVOKEVIRTUAL javax/swing/GroupLayout.createParallelGroup(Ljavax/swing/GroupLayout$Alignment;)Ljavax/swing/GroupLayout$ParallelGroup;
ALOAD 1
GETFIELD az.a Ldg;
BIPUSH -2
ICONST_M1
BIPUSH -2
INVOKEVIRTUAL javax/swing/GroupLayout$ParallelGroup.addComponent(Ljava/awt/Component;III)Ljavax/swing/GroupLayout$ParallelGroup;
ALOAD 1
GETFIELD az.b Ldg;
BIPUSH -2
ICONST_M1
BIPUSH -2
INVOKEVIRTUAL javax/swing/GroupLayout$ParallelGroup.addComponent(Ljava/awt/Component;III)Ljavax/swing/GroupLayout$ParallelGroup;
INVOKEVIRTUAL javax/swing/GroupLayout$SequentialGroup.addGroup(Ljavax/swing/GroupLayout$Group;)Ljavax/swing/GroupLayout$SequentialGroup;
INVOKEVIRTUAL javax/swing/GroupLayout$SequentialGroup.addContainerGap()Ljavax/swing/GroupLayout$SequentialGroup;
INVOKEVIRTUAL javax/swing/GroupLayout$ParallelGroup.addGroup(Ljavax/swing/GroupLayout$Group;)Ljavax/swing/GroupLayout$ParallelGroup;
INVOKEVIRTUAL javax/swing/GroupLayout.setVerticalGroup(Ljavax/swing/GroupLayout$Group;)V
ALOAD 1
GETFIELD az.f Ljavax/swing/JPanel;
NEW java/awt/Color
DUP
SIPUSH 250
SIPUSH 250
SIPUSH 250
INVOKESPECIAL java/awt/Color.<init>(III)V
INVOKEVIRTUAL javax/swing/JPanel.setBackground(Ljava/awt/Color;)V
ALOAD 1
GETFIELD az.f Ljavax/swing/JPanel;
LDC "User:"
INVOKESTATIC javax/swing/BorderFactory.createTitledBorder(Ljava/lang/String;)Ljavax/swing/border/TitledBorder;
INVOKEVIRTUAL javax/swing/JPanel.setBorder(Ljavax/swing/border/Border;)V
ALOAD 1
GETFIELD az.b Ljavax/swing/JComboBox;
NEW java/awt/Color
DUP
SIPUSH 250
SIPUSH 250
SIPUSH 250
INVOKESPECIAL java/awt/Color.<init>(III)V
INVOKEVIRTUAL javax/swing/JComboBox.setBackground(Ljava/awt/Color;)V
ALOAD 1
GETFIELD az.b Ljavax/swing/JComboBox;
NEW java/awt/Font
DUP
LDC "Dialog"
ICONST_0
BIPUSH 12
INVOKESPECIAL java/awt/Font.<init>(Ljava/lang/String;II)V
INVOKEVIRTUAL javax/swing/JComboBox.setFont(Ljava/awt/Font;)V
ALOAD 1
GETFIELD az.b Ljavax/swing/JComboBox;
NEW java/awt/Color
DUP
BIPUSH 97
BIPUSH 97
BIPUSH 97
INVOKESPECIAL java/awt/Color.<init>(III)V
INVOKEVIRTUAL javax/swing/JComboBox.setForeground(Ljava/awt/Color;)V
ALOAD 1
GETFIELD az.b Ljavax/swing/JComboBox;
NEW java/awt/Color
DUP
SIPUSH 250
SIPUSH 250
SIPUSH 250
INVOKESPECIAL java/awt/Color.<init>(III)V
INVOKESTATIC javax/swing/BorderFactory.createLineBorder(Ljava/awt/Color;)Ljavax/swing/border/Border;
INVOKEVIRTUAL javax/swing/JComboBox.setBorder(Ljavax/swing/border/Border;)V
ALOAD 1
GETFIELD az.b Ljavax/swing/JComboBox;
NEW java/awt/Dimension
DUP
BIPUSH 36
BIPUSH 28
INVOKESPECIAL java/awt/Dimension.<init>(II)V
INVOKEVIRTUAL javax/swing/JComboBox.setPreferredSize(Ljava/awt/Dimension;)V
ALOAD 1
GETFIELD az.b Ljavax/swing/JComboBox;
NEW aW
DUP
ALOAD 1
INVOKESPECIAL aW.<init>(Laz;)V
INVOKEVIRTUAL javax/swing/JComboBox.setRenderer(Ljavax/swing/ListCellRenderer;)V
ALOAD 1
GETFIELD az.b Ljavax/swing/JComboBox;
NEW aK
DUP
ALOAD 1
INVOKESPECIAL aK.<init>(Laz;)V
INVOKEVIRTUAL javax/swing/JComboBox.addItemListener(Ljava/awt/event/ItemListener;)V
NEW javax/swing/GroupLayout
DUP
ALOAD 1
GETFIELD az.f Ljavax/swing/JPanel;
INVOKESPECIAL javax/swing/GroupLayout.<init>(Ljava/awt/Container;)V
ASTORE 2
ALOAD 1
GETFIELD az.f Ljavax/swing/JPanel;
ALOAD 2
INVOKEVIRTUAL javax/swing/JPanel.setLayout(Ljava/awt/LayoutManager;)V
ALOAD 2
DUP
GETSTATIC javax/swing/GroupLayout$Alignment.LEADING Ljavax/swing/GroupLayout$Alignment;
INVOKEVIRTUAL javax/swing/GroupLayout.createParallelGroup(Ljavax/swing/GroupLayout$Alignment;)Ljavax/swing/GroupLayout$ParallelGroup;
ALOAD 1
GETFIELD az.b Ljavax/swing/JComboBox;
ICONST_0
ICONST_M1
SIPUSH 32767
INVOKEVIRTUAL javax/swing/GroupLayout$ParallelGroup.addComponent(Ljava/awt/Component;III)Ljavax/swing/GroupLayout$ParallelGroup;
INVOKEVIRTUAL javax/swing/GroupLayout.setHorizontalGroup(Ljavax/swing/GroupLayout$Group;)V
ALOAD 2
DUP
GETSTATIC javax/swing/GroupLayout$Alignment.LEADING Ljavax/swing/GroupLayout$Alignment;
INVOKEVIRTUAL javax/swing/GroupLayout.createParallelGroup(Ljavax/swing/GroupLayout$Alignment;)Ljavax/swing/GroupLayout$ParallelGroup;
ALOAD 2
INVOKEVIRTUAL javax/swing/GroupLayout.createSequentialGroup()Ljavax/swing/GroupLayout$SequentialGroup;
ALOAD 1
GETFIELD az.b Ljavax/swing/JComboBox;
BIPUSH -2
BIPUSH 54
BIPUSH -2
INVOKEVIRTUAL javax/swing/GroupLayout$SequentialGroup.addComponent(Ljava/awt/Component;III)Ljavax/swing/GroupLayout$SequentialGroup;
ICONST_0
ICONST_1
SIPUSH 32767
INVOKEVIRTUAL javax/swing/GroupLayout$SequentialGroup.addGap(III)Ljavax/swing/GroupLayout$SequentialGroup;
INVOKEVIRTUAL javax/swing/GroupLayout$ParallelGroup.addGroup(Ljavax/swing/GroupLayout$Group;)Ljavax/swing/GroupLayout$ParallelGroup;
INVOKEVIRTUAL javax/swing/GroupLayout.setVerticalGroup(Ljavax/swing/GroupLayout$Group;)V
NEW javax/swing/GroupLayout
DUP
ALOAD 1
GETFIELD az.a Ljavax/swing/JPanel;
INVOKESPECIAL javax/swing/GroupLayout.<init>(Ljava/awt/Container;)V
ASTORE 2
ALOAD 1
GETFIELD az.a Ljavax/swing/JPanel;
ALOAD 2
INVOKEVIRTUAL javax/swing/JPanel.setLayout(Ljava/awt/LayoutManager;)V
ALOAD 2
DUP
GETSTATIC javax/swing/GroupLayout$Alignment.LEADING Ljavax/swing/GroupLayout$Alignment;
INVOKEVIRTUAL javax/swing/GroupLayout.createParallelGroup(Ljavax/swing/GroupLayout$Alignment;)Ljavax/swing/GroupLayout$ParallelGroup;
ALOAD 1
GETFIELD az.d LcT;
GETSTATIC javax/swing/GroupLayout$Alignment.TRAILING Ljavax/swing/GroupLayout$Alignment;
BIPUSH -2
ICONST_0
SIPUSH 32767
INVOKEVIRTUAL javax/swing/GroupLayout$ParallelGroup.addComponent(Ljava/awt/Component;Ljavax/swing/GroupLayout$Alignment;III)Ljavax/swing/GroupLayout$ParallelGroup;
ALOAD 1
GETFIELD az.b LcT;
BIPUSH -2
ICONST_0
SIPUSH 32767
INVOKEVIRTUAL javax/swing/GroupLayout$ParallelGroup.addComponent(Ljava/awt/Component;III)Ljavax/swing/GroupLayout$ParallelGroup;
ALOAD 1
GETFIELD az.a LcT;
BIPUSH -2
ICONST_0
SIPUSH 32767
INVOKEVIRTUAL javax/swing/GroupLayout$ParallelGroup.addComponent(Ljava/awt/Component;III)Ljavax/swing/GroupLayout$ParallelGroup;
ALOAD 1
GETFIELD az.c LcT;
BIPUSH -2
ICONST_0
SIPUSH 32767
INVOKEVIRTUAL javax/swing/GroupLayout$ParallelGroup.addComponent(Ljava/awt/Component;III)Ljavax/swing/GroupLayout$ParallelGroup;
ALOAD 1
GETFIELD az.h LcT;
BIPUSH -2
ICONST_0
SIPUSH 32767
INVOKEVIRTUAL javax/swing/GroupLayout$ParallelGroup.addComponent(Ljava/awt/Component;III)Ljavax/swing/GroupLayout$ParallelGroup;
ALOAD 1
GETFIELD az.f LcT;
BIPUSH -2
ICONST_0
SIPUSH 32767
INVOKEVIRTUAL javax/swing/GroupLayout$ParallelGroup.addComponent(Ljava/awt/Component;III)Ljavax/swing/GroupLayout$ParallelGroup;
ALOAD 1
GETFIELD az.e LcT;
BIPUSH -2
ICONST_0
SIPUSH 32767
INVOKEVIRTUAL javax/swing/GroupLayout$ParallelGroup.addComponent(Ljava/awt/Component;III)Ljavax/swing/GroupLayout$ParallelGroup;
ALOAD 1
GETFIELD az.i LcT;
BIPUSH -2
ICONST_0
SIPUSH 32767
INVOKEVIRTUAL javax/swing/GroupLayout$ParallelGroup.addComponent(Ljava/awt/Component;III)Ljavax/swing/GroupLayout$ParallelGroup;
ALOAD 1
GETFIELD az.g LcT;
BIPUSH -2
ICONST_0
SIPUSH 32767
INVOKEVIRTUAL javax/swing/GroupLayout$ParallelGroup.addComponent(Ljava/awt/Component;III)Ljavax/swing/GroupLayout$ParallelGroup;
ALOAD 2
INVOKEVIRTUAL javax/swing/GroupLayout.createSequentialGroup()Ljavax/swing/GroupLayout$SequentialGroup;
ALOAD 1
GETFIELD az.a Ljavax/swing/JComboBox;
ICONST_0
ICONST_M1
SIPUSH 32767
INVOKEVIRTUAL javax/swing/GroupLayout$SequentialGroup.addComponent(Ljava/awt/Component;III)Ljavax/swing/GroupLayout$SequentialGroup;
ICONST_0
ICONST_0
ICONST_0
INVOKEVIRTUAL javax/swing/GroupLayout$SequentialGroup.addGap(III)Ljavax/swing/GroupLayout$SequentialGroup;
ALOAD 1
GETFIELD az.a LcX;
BIPUSH -2
ICONST_M1
BIPUSH -2
INVOKEVIRTUAL javax/swing/GroupLayout$SequentialGroup.addComponent(Ljava/awt/Component;III)Ljavax/swing/GroupLayout$SequentialGroup;
INVOKEVIRTUAL javax/swing/GroupLayout$ParallelGroup.addGroup(Ljavax/swing/GroupLayout$Group;)Ljavax/swing/GroupLayout$ParallelGroup;
ALOAD 1
GETFIELD az.g Ljavax/swing/JPanel;
ICONST_M1
ICONST_M1
SIPUSH 32767
INVOKEVIRTUAL javax/swing/GroupLayout$ParallelGroup.addComponent(Ljava/awt/Component;III)Ljavax/swing/GroupLayout$ParallelGroup;
ALOAD 1
GETFIELD az.f Ljavax/swing/JPanel;
ICONST_M1
ICONST_M1
SIPUSH 32767
INVOKEVIRTUAL javax/swing/GroupLayout$ParallelGroup.addComponent(Ljava/awt/Component;III)Ljavax/swing/GroupLayout$ParallelGroup;
INVOKEVIRTUAL javax/swing/GroupLayout.setHorizontalGroup(Ljavax/swing/GroupLayout$Group;)V
ALOAD 2
DUP
GETSTATIC javax/swing/GroupLayout$Alignment.LEADING Ljavax/swing/GroupLayout$Alignment;
INVOKEVIRTUAL javax/swing/GroupLayout.createParallelGroup(Ljavax/swing/GroupLayout$Alignment;)Ljavax/swing/GroupLayout$ParallelGroup;
ALOAD 2
INVOKEVIRTUAL javax/swing/GroupLayout.createSequentialGroup()Ljavax/swing/GroupLayout$SequentialGroup;
ALOAD 2
GETSTATIC javax/swing/GroupLayout$Alignment.LEADING Ljavax/swing/GroupLayout$Alignment;
ICONST_0
INVOKEVIRTUAL javax/swing/GroupLayout.createParallelGroup(Ljavax/swing/GroupLayout$Alignment;Z)Ljavax/swing/GroupLayout$ParallelGroup;
ALOAD 1
GETFIELD az.a Ljavax/swing/JComboBox;
ICONST_M1
BIPUSH 54
SIPUSH 32767
INVOKEVIRTUAL javax/swing/GroupLayout$ParallelGroup.addComponent(Ljava/awt/Component;III)Ljavax/swing/GroupLayout$ParallelGroup;
ALOAD 1
GETFIELD az.a LcX;
ICONST_M1
ICONST_M1
SIPUSH 32767
INVOKEVIRTUAL javax/swing/GroupLayout$ParallelGroup.addComponent(Ljava/awt/Component;III)Ljavax/swing/GroupLayout$ParallelGroup;
INVOKEVIRTUAL javax/swing/GroupLayout$SequentialGroup.addGroup(Ljavax/swing/GroupLayout$Group;)Ljavax/swing/GroupLayout$SequentialGroup;
GETSTATIC javax/swing/LayoutStyle$ComponentPlacement.RELATED Ljavax/swing/LayoutStyle$ComponentPlacement;
INVOKEVIRTUAL javax/swing/GroupLayout$SequentialGroup.addPreferredGap(Ljavax/swing/LayoutStyle$ComponentPlacement;)Ljavax/swing/GroupLayout$SequentialGroup;
ALOAD 1
GETFIELD az.g Ljavax/swing/JPanel;
BIPUSH -2
ICONST_M1
BIPUSH -2
INVOKEVIRTUAL javax/swing/GroupLayout$SequentialGroup.addComponent(Ljava/awt/Component;III)Ljavax/swing/GroupLayout$SequentialGroup;
GETSTATIC javax/swing/LayoutStyle$ComponentPlacement.RELATED Ljavax/swing/LayoutStyle$ComponentPlacement;
INVOKEVIRTUAL javax/swing/GroupLayout$SequentialGroup.addPreferredGap(Ljavax/swing/LayoutStyle$ComponentPlacement;)Ljavax/swing/GroupLayout$SequentialGroup;
ALOAD 1
GETFIELD az.f Ljavax/swing/JPanel;
BIPUSH -2
ICONST_M1
BIPUSH -2
INVOKEVIRTUAL javax/swing/GroupLayout$SequentialGroup.addComponent(Ljava/awt/Component;III)Ljavax/swing/GroupLayout$SequentialGroup;
GETSTATIC javax/swing/LayoutStyle$ComponentPlacement.RELATED Ljavax/swing/LayoutStyle$ComponentPlacement;
INVOKEVIRTUAL javax/swing/GroupLayout$SequentialGroup.addPreferredGap(Ljavax/swing/LayoutStyle$ComponentPlacement;)Ljavax/swing/GroupLayout$SequentialGroup;
ALOAD 1
GETFIELD az.d LcT;
BIPUSH -2
BIPUSH 32
BIPUSH -2
INVOKEVIRTUAL javax/swing/GroupLayout$SequentialGroup.addComponent(Ljava/awt/Component;III)Ljavax/swing/GroupLayout$SequentialGroup;
ICONST_0
ICONST_0
ICONST_0
INVOKEVIRTUAL javax/swing/GroupLayout$SequentialGroup.addGap(III)Ljavax/swing/GroupLayout$SequentialGroup;
ALOAD 1
GETFIELD az.a LcT;
BIPUSH -2
BIPUSH 32
BIPUSH -2
INVOKEVIRTUAL javax/swing/GroupLayout$SequentialGroup.addComponent(Ljava/awt/Component;III)Ljavax/swing/GroupLayout$SequentialGroup;
ICONST_0
ICONST_0
ICONST_0
INVOKEVIRTUAL javax/swing/GroupLayout$SequentialGroup.addGap(III)Ljavax/swing/GroupLayout$SequentialGroup;
ALOAD 1
GETFIELD az.b LcT;
BIPUSH -2
BIPUSH 32
BIPUSH -2
INVOKEVIRTUAL javax/swing/GroupLayout$SequentialGroup.addComponent(Ljava/awt/Component;III)Ljavax/swing/GroupLayout$SequentialGroup;
ICONST_0
ICONST_0
ICONST_0
INVOKEVIRTUAL javax/swing/GroupLayout$SequentialGroup.addGap(III)Ljavax/swing/GroupLayout$SequentialGroup;
ALOAD 1
GETFIELD az.c LcT;
BIPUSH -2
BIPUSH 32
BIPUSH -2
INVOKEVIRTUAL javax/swing/GroupLayout$SequentialGroup.addComponent(Ljava/awt/Component;III)Ljavax/swing/GroupLayout$SequentialGroup;
ICONST_0
ICONST_0
ICONST_0
INVOKEVIRTUAL javax/swing/GroupLayout$SequentialGroup.addGap(III)Ljavax/swing/GroupLayout$SequentialGroup;
ALOAD 1
GETFIELD az.f LcT;
BIPUSH -2
BIPUSH 32
BIPUSH -2
INVOKEVIRTUAL javax/swing/GroupLayout$SequentialGroup.addComponent(Ljava/awt/Component;III)Ljavax/swing/GroupLayout$SequentialGroup;
ICONST_0
ICONST_0
ICONST_0
INVOKEVIRTUAL javax/swing/GroupLayout$SequentialGroup.addGap(III)Ljavax/swing/GroupLayout$SequentialGroup;
ALOAD 1
GETFIELD az.e LcT;
BIPUSH -2
BIPUSH 32
BIPUSH -2
INVOKEVIRTUAL javax/swing/GroupLayout$SequentialGroup.addComponent(Ljava/awt/Component;III)Ljavax/swing/GroupLayout$SequentialGroup;
ICONST_0
ICONST_0
ICONST_0
INVOKEVIRTUAL javax/swing/GroupLayout$SequentialGroup.addGap(III)Ljavax/swing/GroupLayout$SequentialGroup;
ALOAD 1
GETFIELD az.i LcT;
BIPUSH -2
BIPUSH 32
BIPUSH -2
INVOKEVIRTUAL javax/swing/GroupLayout$SequentialGroup.addComponent(Ljava/awt/Component;III)Ljavax/swing/GroupLayout$SequentialGroup;
BIPUSH 63
BIPUSH 63
BIPUSH 63
INVOKEVIRTUAL javax/swing/GroupLayout$SequentialGroup.addGap(III)Ljavax/swing/GroupLayout$SequentialGroup;
ALOAD 1
GETFIELD az.g LcT;
BIPUSH -2
BIPUSH 32
BIPUSH -2
INVOKEVIRTUAL javax/swing/GroupLayout$SequentialGroup.addComponent(Ljava/awt/Component;III)Ljavax/swing/GroupLayout$SequentialGroup;
GETSTATIC javax/swing/LayoutStyle$ComponentPlacement.RELATED Ljavax/swing/LayoutStyle$ComponentPlacement;
BIPUSH 8
SIPUSH 32767
INVOKEVIRTUAL javax/swing/GroupLayout$SequentialGroup.addPreferredGap(Ljavax/swing/LayoutStyle$ComponentPlacement;II)Ljavax/swing/GroupLayout$SequentialGroup;
ALOAD 1
GETFIELD az.h LcT;
BIPUSH -2
BIPUSH 32
BIPUSH -2
INVOKEVIRTUAL javax/swing/GroupLayout$SequentialGroup.addComponent(Ljava/awt/Component;III)Ljavax/swing/GroupLayout$SequentialGroup;
INVOKEVIRTUAL javax/swing/GroupLayout$ParallelGroup.addGroup(Ljavax/swing/GroupLayout$Group;)Ljavax/swing/GroupLayout$ParallelGroup;
INVOKEVIRTUAL javax/swing/GroupLayout.setVerticalGroup(Ljavax/swing/GroupLayout$Group;)V
ALOAD 1
GETFIELD az.f Ljavax/swing/JPanel;
INVOKEVIRTUAL javax/swing/JPanel.getAccessibleContext()Ljavax/accessibility/AccessibleContext;
LDC "User:"
INVOKEVIRTUAL javax/accessibility/AccessibleContext.setAccessibleName(Ljava/lang/String;)V
ALOAD 1
GETFIELD az.d Ljavax/swing/JPanel;
NEW java/awt/Color
DUP
SIPUSH 250
SIPUSH 250
SIPUSH 250
INVOKESPECIAL java/awt/Color.<init>(III)V
INVOKEVIRTUAL javax/swing/JPanel.setBackground(Ljava/awt/Color;)V
ALOAD 1
GETFIELD az.d Ljavax/swing/JPanel;
NEW java/awt/Color
DUP
SIPUSH 217
SIPUSH 217
SIPUSH 217
INVOKESPECIAL java/awt/Color.<init>(III)V
INVOKESTATIC javax/swing/BorderFactory.createLineBorder(Ljava/awt/Color;)Ljavax/swing/border/Border;
INVOKEVIRTUAL javax/swing/JPanel.setBorder(Ljavax/swing/border/Border;)V
ALOAD 1
GETFIELD az.d Ljavax/swing/JPanel;
NEW java/awt/Dimension
DUP
BIPUSH 100
BIPUSH 32
INVOKESPECIAL java/awt/Dimension.<init>(II)V
INVOKEVIRTUAL javax/swing/JPanel.setMinimumSize(Ljava/awt/Dimension;)V
ALOAD 1
GETFIELD az.d Ljavax/swing/JPanel;
NEW java/awt/Dimension
DUP
SIPUSH 137
BIPUSH 32
INVOKESPECIAL java/awt/Dimension.<init>(II)V
INVOKEVIRTUAL javax/swing/JPanel.setPreferredSize(Ljava/awt/Dimension;)V
ALOAD 1
GETFIELD az.a Ljavax/swing/JLabel;
NEW java/awt/Font
DUP
LDC "Dialog"
ICONST_1
BIPUSH 10
INVOKESPECIAL java/awt/Font.<init>(Ljava/lang/String;II)V
INVOKEVIRTUAL javax/swing/JLabel.setFont(Ljava/awt/Font;)V
ALOAD 1
GETFIELD az.a Ljavax/swing/JLabel;
NEW java/awt/Color
DUP
BIPUSH 97
BIPUSH 97
BIPUSH 97
INVOKESPECIAL java/awt/Color.<init>(III)V
INVOKEVIRTUAL javax/swing/JLabel.setForeground(Ljava/awt/Color;)V
ALOAD 1
GETFIELD az.a Ljavax/swing/JLabel;
ICONST_4
INVOKEVIRTUAL javax/swing/JLabel.setHorizontalAlignment(I)V
ALOAD 1
GETFIELD az.a Ljavax/swing/JSeparator;
NEW java/awt/Color
DUP
SIPUSH 250
SIPUSH 250
SIPUSH 250
INVOKESPECIAL java/awt/Color.<init>(III)V
INVOKEVIRTUAL javax/swing/JSeparator.setBackground(Ljava/awt/Color;)V
ALOAD 1
GETFIELD az.a Ljavax/swing/JSeparator;
NEW java/awt/Color
DUP
SIPUSH 217
SIPUSH 217
SIPUSH 217
INVOKESPECIAL java/awt/Color.<init>(III)V
INVOKEVIRTUAL javax/swing/JSeparator.setForeground(Ljava/awt/Color;)V
ALOAD 1
GETFIELD az.a Ljavax/swing/JSeparator;
ICONST_1
INVOKEVIRTUAL javax/swing/JSeparator.setOrientation(I)V
ALOAD 1
GETFIELD az.a Ljavax/swing/JProgressBar;
NEW java/awt/Color
DUP
BIPUSH 76
SIPUSH 175
BIPUSH 80
INVOKESPECIAL java/awt/Color.<init>(III)V
INVOKEVIRTUAL javax/swing/JProgressBar.setForeground(Ljava/awt/Color;)V
ALOAD 1
GETFIELD az.a Ljavax/swing/JProgressBar;
LDC ""
INVOKEVIRTUAL javax/swing/JProgressBar.setToolTipText(Ljava/lang/String;)V
ALOAD 1
GETFIELD az.a Ljavax/swing/JProgressBar;
ICONST_1
INVOKEVIRTUAL javax/swing/JProgressBar.setStringPainted(Z)V
ALOAD 1
GETFIELD az.a Ljavax/swing/JProgressBar;
NEW aM
DUP
ALOAD 1
INVOKESPECIAL aM.<init>(Laz;)V
INVOKEVIRTUAL javax/swing/JProgressBar.addMouseListener(Ljava/awt/event/MouseListener;)V
ALOAD 1
GETFIELD az.c Ljavax/swing/JLabel;
NEW java/awt/Font
DUP
LDC "Dialog"
ICONST_0
BIPUSH 12
INVOKESPECIAL java/awt/Font.<init>(Ljava/lang/String;II)V
INVOKEVIRTUAL javax/swing/JLabel.setFont(Ljava/awt/Font;)V
ALOAD 1
GETFIELD az.c Ljavax/swing/JLabel;
NEW java/awt/Color
DUP
BIPUSH 97
BIPUSH 97
BIPUSH 97
INVOKESPECIAL java/awt/Color.<init>(III)V
INVOKEVIRTUAL javax/swing/JLabel.setForeground(Ljava/awt/Color;)V
ALOAD 1
GETFIELD az.c Ljavax/swing/JLabel;
ICONST_4
INVOKEVIRTUAL javax/swing/JLabel.setHorizontalAlignment(I)V
NEW javax/swing/GroupLayout
DUP
ALOAD 1
GETFIELD az.d Ljavax/swing/JPanel;
INVOKESPECIAL javax/swing/GroupLayout.<init>(Ljava/awt/Container;)V
ASTORE 2
ALOAD 1
GETFIELD az.d Ljavax/swing/JPanel;
ALOAD 2
INVOKEVIRTUAL javax/swing/JPanel.setLayout(Ljava/awt/LayoutManager;)V
ALOAD 2
DUP
GETSTATIC javax/swing/GroupLayout$Alignment.LEADING Ljavax/swing/GroupLayout$Alignment;
INVOKEVIRTUAL javax/swing/GroupLayout.createParallelGroup(Ljavax/swing/GroupLayout$Alignment;)Ljavax/swing/GroupLayout$ParallelGroup;
GETSTATIC javax/swing/GroupLayout$Alignment.TRAILING Ljavax/swing/GroupLayout$Alignment;
ALOAD 2
INVOKEVIRTUAL javax/swing/GroupLayout.createSequentialGroup()Ljavax/swing/GroupLayout$SequentialGroup;
ALOAD 1
GETFIELD az.a Ljavax/swing/JProgressBar;
BIPUSH -2
SIPUSH 198
BIPUSH -2
INVOKEVIRTUAL javax/swing/GroupLayout$SequentialGroup.addComponent(Ljava/awt/Component;III)Ljavax/swing/GroupLayout$SequentialGroup;
BIPUSH 6
BIPUSH 6
BIPUSH 6
INVOKEVIRTUAL javax/swing/GroupLayout$SequentialGroup.addGap(III)Ljavax/swing/GroupLayout$SequentialGroup;
ALOAD 1
GETFIELD az.c Ljavax/swing/JLabel;
ICONST_M1
SIPUSH 592
SIPUSH 32767
INVOKEVIRTUAL javax/swing/GroupLayout$SequentialGroup.addComponent(Ljava/awt/Component;III)Ljavax/swing/GroupLayout$SequentialGroup;
BIPUSH 6
BIPUSH 6
BIPUSH 6
INVOKEVIRTUAL javax/swing/GroupLayout$SequentialGroup.addGap(III)Ljavax/swing/GroupLayout$SequentialGroup;
ALOAD 1
GETFIELD az.a Ljavax/swing/JSeparator;
BIPUSH -2
BIPUSH 6
BIPUSH -2
INVOKEVIRTUAL javax/swing/GroupLayout$SequentialGroup.addComponent(Ljava/awt/Component;III)Ljavax/swing/GroupLayout$SequentialGroup;
ICONST_0
ICONST_0
ICONST_0
INVOKEVIRTUAL javax/swing/GroupLayout$SequentialGroup.addGap(III)Ljavax/swing/GroupLayout$SequentialGroup;
ALOAD 1
GETFIELD az.a Ljavax/swing/JLabel;
BIPUSH -2
SIPUSH 128
BIPUSH -2
INVOKEVIRTUAL javax/swing/GroupLayout$SequentialGroup.addComponent(Ljava/awt/Component;III)Ljavax/swing/GroupLayout$SequentialGroup;
BIPUSH 6
BIPUSH 6
BIPUSH 6
INVOKEVIRTUAL javax/swing/GroupLayout$SequentialGroup.addGap(III)Ljavax/swing/GroupLayout$SequentialGroup;
INVOKEVIRTUAL javax/swing/GroupLayout$ParallelGroup.addGroup(Ljavax/swing/GroupLayout$Alignment;Ljavax/swing/GroupLayout$Group;)Ljavax/swing/GroupLayout$ParallelGroup;
INVOKEVIRTUAL javax/swing/GroupLayout.setHorizontalGroup(Ljavax/swing/GroupLayout$Group;)V
ALOAD 2
DUP
GETSTATIC javax/swing/GroupLayout$Alignment.LEADING Ljavax/swing/GroupLayout$Alignment;
INVOKEVIRTUAL javax/swing/GroupLayout.createParallelGroup(Ljavax/swing/GroupLayout$Alignment;)Ljavax/swing/GroupLayout$ParallelGroup;
ALOAD 1
GETFIELD az.a Ljavax/swing/JSeparator;
INVOKEVIRTUAL javax/swing/GroupLayout$ParallelGroup.addComponent(Ljava/awt/Component;)Ljavax/swing/GroupLayout$ParallelGroup;
ALOAD 1
GETFIELD az.a Ljavax/swing/JLabel;
GETSTATIC javax/swing/GroupLayout$Alignment.TRAILING Ljavax/swing/GroupLayout$Alignment;
ICONST_M1
ICONST_M1
SIPUSH 32767
INVOKEVIRTUAL javax/swing/GroupLayout$ParallelGroup.addComponent(Ljava/awt/Component;Ljavax/swing/GroupLayout$Alignment;III)Ljavax/swing/GroupLayout$ParallelGroup;
ALOAD 1
GETFIELD az.a Ljavax/swing/JProgressBar;
GETSTATIC javax/swing/GroupLayout$Alignment.TRAILING Ljavax/swing/GroupLayout$Alignment;
ICONST_M1
BIPUSH 30
SIPUSH 32767
INVOKEVIRTUAL javax/swing/GroupLayout$ParallelGroup.addComponent(Ljava/awt/Component;Ljavax/swing/GroupLayout$Alignment;III)Ljavax/swing/GroupLayout$ParallelGroup;
ALOAD 1
GETFIELD az.c Ljavax/swing/JLabel;
GETSTATIC javax/swing/GroupLayout$Alignment.TRAILING Ljavax/swing/GroupLayout$Alignment;
ICONST_M1
ICONST_M1
SIPUSH 32767
INVOKEVIRTUAL javax/swing/GroupLayout$ParallelGroup.addComponent(Ljava/awt/Component;Ljavax/swing/GroupLayout$Alignment;III)Ljavax/swing/GroupLayout$ParallelGroup;
INVOKEVIRTUAL javax/swing/GroupLayout.setVerticalGroup(Ljavax/swing/GroupLayout$Group;)V
NEW javax/swing/GroupLayout
DUP
ALOAD 1
GETFIELD az.c Ljavax/swing/JPanel;
INVOKESPECIAL javax/swing/GroupLayout.<init>(Ljava/awt/Container;)V
ASTORE 2
ALOAD 1
GETFIELD az.c Ljavax/swing/JPanel;
ALOAD 2
INVOKEVIRTUAL javax/swing/JPanel.setLayout(Ljava/awt/LayoutManager;)V
ALOAD 2
DUP
GETSTATIC javax/swing/GroupLayout$Alignment.LEADING Ljavax/swing/GroupLayout$Alignment;
INVOKEVIRTUAL javax/swing/GroupLayout.createParallelGroup(Ljavax/swing/GroupLayout$Alignment;)Ljavax/swing/GroupLayout$ParallelGroup;
ALOAD 1
GETFIELD az.e Ljavax/swing/JPanel;
ICONST_M1
ICONST_M1
SIPUSH 32767
INVOKEVIRTUAL javax/swing/GroupLayout$ParallelGroup.addComponent(Ljava/awt/Component;III)Ljavax/swing/GroupLayout$ParallelGroup;
ALOAD 2
INVOKEVIRTUAL javax/swing/GroupLayout.createSequentialGroup()Ljavax/swing/GroupLayout$SequentialGroup;
ALOAD 1
GETFIELD az.a Ljavax/swing/JPanel;
BIPUSH -2
ICONST_M1
BIPUSH -2
INVOKEVIRTUAL javax/swing/GroupLayout$SequentialGroup.addComponent(Ljava/awt/Component;III)Ljavax/swing/GroupLayout$SequentialGroup;
ICONST_0
ICONST_0
ICONST_0
INVOKEVIRTUAL javax/swing/GroupLayout$SequentialGroup.addGap(III)Ljavax/swing/GroupLayout$SequentialGroup;
ALOAD 1
GETFIELD az.b Ljavax/swing/JPanel;
ICONST_M1
ICONST_M1
SIPUSH 32767
INVOKEVIRTUAL javax/swing/GroupLayout$SequentialGroup.addComponent(Ljava/awt/Component;III)Ljavax/swing/GroupLayout$SequentialGroup;
INVOKEVIRTUAL javax/swing/GroupLayout$ParallelGroup.addGroup(Ljavax/swing/GroupLayout$Group;)Ljavax/swing/GroupLayout$ParallelGroup;
ALOAD 1
GETFIELD az.d Ljavax/swing/JPanel;
ICONST_M1
SIPUSH 944
SIPUSH 32767
INVOKEVIRTUAL javax/swing/GroupLayout$ParallelGroup.addComponent(Ljava/awt/Component;III)Ljavax/swing/GroupLayout$ParallelGroup;
INVOKEVIRTUAL javax/swing/GroupLayout.setHorizontalGroup(Ljavax/swing/GroupLayout$Group;)V
ALOAD 2
DUP
GETSTATIC javax/swing/GroupLayout$Alignment.LEADING Ljavax/swing/GroupLayout$Alignment;
INVOKEVIRTUAL javax/swing/GroupLayout.createParallelGroup(Ljavax/swing/GroupLayout$Alignment;)Ljavax/swing/GroupLayout$ParallelGroup;
ALOAD 2
INVOKEVIRTUAL javax/swing/GroupLayout.createSequentialGroup()Ljavax/swing/GroupLayout$SequentialGroup;
ICONST_0
ICONST_0
ICONST_0
INVOKEVIRTUAL javax/swing/GroupLayout$SequentialGroup.addGap(III)Ljavax/swing/GroupLayout$SequentialGroup;
ALOAD 1
GETFIELD az.e Ljavax/swing/JPanel;
BIPUSH -2
ICONST_M1
BIPUSH -2
INVOKEVIRTUAL javax/swing/GroupLayout$SequentialGroup.addComponent(Ljava/awt/Component;III)Ljavax/swing/GroupLayout$SequentialGroup;
ICONST_0
ICONST_0
ICONST_0
INVOKEVIRTUAL javax/swing/GroupLayout$SequentialGroup.addGap(III)Ljavax/swing/GroupLayout$SequentialGroup;
ALOAD 2
GETSTATIC javax/swing/GroupLayout$Alignment.LEADING Ljavax/swing/GroupLayout$Alignment;
INVOKEVIRTUAL javax/swing/GroupLayout.createParallelGroup(Ljavax/swing/GroupLayout$Alignment;)Ljavax/swing/GroupLayout$ParallelGroup;
ALOAD 1
GETFIELD az.b Ljavax/swing/JPanel;
ICONST_M1
ICONST_M1
SIPUSH 32767
INVOKEVIRTUAL javax/swing/GroupLayout$ParallelGroup.addComponent(Ljava/awt/Component;III)Ljavax/swing/GroupLayout$ParallelGroup;
ALOAD 1
GETFIELD az.a Ljavax/swing/JPanel;
ICONST_M1
ICONST_M1
SIPUSH 32767
INVOKEVIRTUAL javax/swing/GroupLayout$ParallelGroup.addComponent(Ljava/awt/Component;III)Ljavax/swing/GroupLayout$ParallelGroup;
INVOKEVIRTUAL javax/swing/GroupLayout$SequentialGroup.addGroup(Ljavax/swing/GroupLayout$Group;)Ljavax/swing/GroupLayout$SequentialGroup;
ICONST_0
ICONST_0
ICONST_0
INVOKEVIRTUAL javax/swing/GroupLayout$SequentialGroup.addGap(III)Ljavax/swing/GroupLayout$SequentialGroup;
ALOAD 1
GETFIELD az.d Ljavax/swing/JPanel;
BIPUSH -2
ICONST_M1
BIPUSH -2
INVOKEVIRTUAL javax/swing/GroupLayout$SequentialGroup.addComponent(Ljava/awt/Component;III)Ljavax/swing/GroupLayout$SequentialGroup;
INVOKEVIRTUAL javax/swing/GroupLayout$ParallelGroup.addGroup(Ljavax/swing/GroupLayout$Group;)Ljavax/swing/GroupLayout$ParallelGroup;
INVOKEVIRTUAL javax/swing/GroupLayout.setVerticalGroup(Ljavax/swing/GroupLayout$Group;)V
NEW javax/swing/GroupLayout
DUP
ALOAD 1
INVOKEVIRTUAL az.getContentPane()Ljava/awt/Container;
INVOKESPECIAL javax/swing/GroupLayout.<init>(Ljava/awt/Container;)V
ASTORE 2
ALOAD 1
INVOKEVIRTUAL az.getContentPane()Ljava/awt/Container;
ALOAD 2
INVOKEVIRTUAL java/awt/Container.setLayout(Ljava/awt/LayoutManager;)V
ALOAD 2
DUP
GETSTATIC javax/swing/GroupLayout$Alignment.LEADING Ljavax/swing/GroupLayout$Alignment;
INVOKEVIRTUAL javax/swing/GroupLayout.createParallelGroup(Ljavax/swing/GroupLayout$Alignment;)Ljavax/swing/GroupLayout$ParallelGroup;
ALOAD 2
INVOKEVIRTUAL javax/swing/GroupLayout.createSequentialGroup()Ljavax/swing/GroupLayout$SequentialGroup;
ICONST_0
ICONST_0
ICONST_0
INVOKEVIRTUAL javax/swing/GroupLayout$SequentialGroup.addGap(III)Ljavax/swing/GroupLayout$SequentialGroup;
ALOAD 1
GETFIELD az.c Ljavax/swing/JPanel;
ICONST_M1
ICONST_M1
SIPUSH 32767
INVOKEVIRTUAL javax/swing/GroupLayout$SequentialGroup.addComponent(Ljava/awt/Component;III)Ljavax/swing/GroupLayout$SequentialGroup;
INVOKEVIRTUAL javax/swing/GroupLayout$ParallelGroup.addGroup(Ljavax/swing/GroupLayout$Group;)Ljavax/swing/GroupLayout$ParallelGroup;
INVOKEVIRTUAL javax/swing/GroupLayout.setHorizontalGroup(Ljavax/swing/GroupLayout$Group;)V
ALOAD 2
DUP
GETSTATIC javax/swing/GroupLayout$Alignment.LEADING Ljavax/swing/GroupLayout$Alignment;
INVOKEVIRTUAL javax/swing/GroupLayout.createParallelGroup(Ljavax/swing/GroupLayout$Alignment;)Ljavax/swing/GroupLayout$ParallelGroup;
ALOAD 1
GETFIELD az.c Ljavax/swing/JPanel;
ICONST_M1
ICONST_M1
SIPUSH 32767
INVOKEVIRTUAL javax/swing/GroupLayout$ParallelGroup.addComponent(Ljava/awt/Component;III)Ljavax/swing/GroupLayout$ParallelGroup;
INVOKEVIRTUAL javax/swing/GroupLayout.setVerticalGroup(Ljavax/swing/GroupLayout$Group;)V
ALOAD 1
INVOKEVIRTUAL az.pack()V
ALOAD this
GETFIELD az.a Ljavax/swing/JButton;
ALOAD this
GETFIELD az.a LaU;
INVOKEVIRTUAL javax/swing/JButton.addMouseListener(Ljava/awt/event/MouseListener;)V
ALOAD this
GETFIELD az.c Ljavax/swing/JButton;
ALOAD this
GETFIELD az.a LaU;
INVOKEVIRTUAL javax/swing/JButton.addMouseListener(Ljava/awt/event/MouseListener;)V
ALOAD this
GETFIELD az.b Ljavax/swing/JButton;
ALOAD this
GETFIELD az.a LaU;
INVOKEVIRTUAL javax/swing/JButton.addMouseListener(Ljava/awt/event/MouseListener;)V
NEW aX
DUP
ALOAD this
INVOKESPECIAL aX.<init>(Laz;)V
ASTORE 1
ALOAD this
ALOAD 1
INVOKEVIRTUAL az.addMouseListener(Ljava/awt/event/MouseListener;)V
ALOAD this
ALOAD 1
INVOKEVIRTUAL az.addMouseMotionListener(Ljava/awt/event/MouseMotionListener;)V
ALOAD this
INVOKESPECIAL az.c()V
ALOAD this
INVOKESPECIAL az.d()V
ALOAD this
NEW aA
DUP
ALOAD this
INVOKESPECIAL aA.<init>(Laz;)V
PUTFIELD az.a LH;
ALOAD this
INVOKESPECIAL az.e()V
NEW javax/swing/Timer
DUP
SIPUSH 1000
ALOAD this
INVOKEDYNAMIC actionPerformed (Laz;)Ljava/awt/event/ActionListener; ${H_META} args[(Ljava/awt/event/ActionEvent;)V, handle[H_INVOKESPECIAL az.a(Ljava/awt/event/ActionEvent;)V], (Ljava/awt/event/ActionEvent;)V]
INVOKESPECIAL javax/swing/Timer.<init>(ILjava/awt/event/ActionListener;)V
INVOKEVIRTUAL javax/swing/Timer.start()V
LDC "Expert_Settings"
INVOKESTATIC ae.a(Ljava/lang/String;)Ljava/lang/String;
INVOKESTATIC java/lang/Boolean.valueOf(Ljava/lang/String;)Ljava/lang/Boolean;
INVOKEVIRTUAL java/lang/Boolean.booleanValue()Z
IFNE B
ALOAD this
GETFIELD az.i LcT;
ICONST_0
INVOKEVIRTUAL cT.setVisible(Z)V
B:
LDC "SuRoot"
INVOKESTATIC ae.a(Ljava/lang/String;)Ljava/lang/String;
INVOKESTATIC java/lang/Boolean.valueOf(Ljava/lang/String;)Ljava/lang/Boolean;
INVOKEVIRTUAL java/lang/Boolean.booleanValue()Z
IFNE C
ALOAD this
GETFIELD az.a LcX;
ICONST_0
INVOKEVIRTUAL cX.setVisible(Z)V
C:
ALOAD this
INVOKESPECIAL az.f()V
RETURN
D:
E: